{
"meta":{"test_sets":[],"test_metrics":[],"learn_metrics":[{"best_value":"Min","name":"RMSE"}],"launch_mode":"Train","parameters":"","iteration_count":1000,"learn_sets":["learn"],"name":"experiment"},
"iterations":[
{"learn":[14.61268541],"iteration":0,"passed_time":0.1352971609,"remaining_time":135.1618637},
{"learn":[14.23196558],"iteration":1,"passed_time":0.1358347876,"remaining_time":67.78155902},
{"learn":[13.86674177],"iteration":2,"passed_time":0.1363767152,"remaining_time":45.32252836},
{"learn":[13.49946468],"iteration":3,"passed_time":0.1368984722,"remaining_time":34.08771959},
{"learn":[13.16661202],"iteration":4,"passed_time":0.1374325123,"remaining_time":27.34906994},
{"learn":[12.85632158],"iteration":5,"passed_time":0.1379383996,"remaining_time":22.85179486},
{"learn":[12.56784336],"iteration":6,"passed_time":0.1384554478,"remaining_time":19.64089423},
{"learn":[12.31617801],"iteration":7,"passed_time":0.1389733476,"remaining_time":17.2326951},
{"learn":[12.01509946],"iteration":8,"passed_time":0.1394944133,"remaining_time":15.35988484},
{"learn":[11.71512571],"iteration":9,"passed_time":0.1400334427,"remaining_time":13.86331082},
{"learn":[11.43264457],"iteration":10,"passed_time":0.1406240486,"remaining_time":12.64338037},
{"learn":[11.17973129],"iteration":11,"passed_time":0.1412249639,"remaining_time":11.62752202},
{"learn":[10.93746433],"iteration":12,"passed_time":0.1417973958,"remaining_time":10.76569459},
{"learn":[10.69387075],"iteration":13,"passed_time":0.1424236284,"remaining_time":10.03069269},
{"learn":[10.4615922],"iteration":14,"passed_time":0.1429945776,"remaining_time":9.38997726},
{"learn":[10.2299235],"iteration":15,"passed_time":0.1436395653,"remaining_time":8.833833269},
{"learn":[10.01419731],"iteration":16,"passed_time":0.1442047036,"remaining_time":8.33842492},
{"learn":[9.795856918],"iteration":17,"passed_time":0.1447997378,"remaining_time":7.899630142},
{"learn":[9.60040151],"iteration":18,"passed_time":0.14534558,"remaining_time":7.504421787},
{"learn":[9.418664989],"iteration":19,"passed_time":0.1459138841,"remaining_time":7.149780323},
{"learn":[9.249278645],"iteration":20,"passed_time":0.1465144187,"remaining_time":6.830362662},
{"learn":[9.090113396],"iteration":21,"passed_time":0.1471239501,"remaining_time":6.540328326},
{"learn":[8.909548708],"iteration":22,"passed_time":0.1476886976,"remaining_time":6.273559024},
{"learn":[8.740140208],"iteration":23,"passed_time":0.1483320122,"remaining_time":6.032168498},
{"learn":[8.59377682],"iteration":24,"passed_time":0.1489538667,"remaining_time":5.809200801},
{"learn":[8.453885414],"iteration":25,"passed_time":0.1495388421,"remaining_time":5.601955085},
{"learn":[8.317732234],"iteration":26,"passed_time":0.1501227956,"remaining_time":5.409980745},
{"learn":[8.180896085],"iteration":27,"passed_time":0.1506931837,"remaining_time":5.231206233},
{"learn":[8.053220863],"iteration":28,"passed_time":0.15126796,"remaining_time":5.064868591},
{"learn":[7.924234474],"iteration":29,"passed_time":0.1518623731,"remaining_time":4.910216729},
{"learn":[7.818879511],"iteration":30,"passed_time":0.1524659834,"remaining_time":4.765791544},
{"learn":[7.719346395],"iteration":31,"passed_time":0.1530820369,"remaining_time":4.630731618},
{"learn":[7.624163594],"iteration":32,"passed_time":0.1536488984,"remaining_time":4.502378327},
{"learn":[7.524952543],"iteration":33,"passed_time":0.1542892074,"remaining_time":4.383628659},
{"learn":[7.424464745],"iteration":34,"passed_time":0.1548742931,"remaining_time":4.270105509},
{"learn":[7.327482321],"iteration":35,"passed_time":0.1554956967,"remaining_time":4.163829211},
{"learn":[7.238666841],"iteration":36,"passed_time":0.1560967121,"remaining_time":4.062733345},
{"learn":[7.158842395],"iteration":37,"passed_time":0.1567316711,"remaining_time":3.96778599},
{"learn":[7.074348246],"iteration":38,"passed_time":0.157353205,"remaining_time":3.877344358},
{"learn":[6.992269093],"iteration":39,"passed_time":0.1579806098,"remaining_time":3.791534636},
{"learn":[6.925219745],"iteration":40,"passed_time":0.1585619985,"remaining_time":3.708803819},
{"learn":[6.86013671],"iteration":41,"passed_time":0.1591627935,"remaining_time":3.630427529},
{"learn":[6.786739622],"iteration":42,"passed_time":0.1597614245,"remaining_time":3.555620541},
{"learn":[6.73057926],"iteration":43,"passed_time":0.160389711,"remaining_time":3.484830994},
{"learn":[6.666356486],"iteration":44,"passed_time":0.1610021278,"remaining_time":3.416822934},
{"learn":[6.606182832],"iteration":45,"passed_time":0.1616137331,"remaining_time":3.35172829},
{"learn":[6.547854615],"iteration":46,"passed_time":0.162258811,"remaining_time":3.290056317},
{"learn":[6.49240675],"iteration":47,"passed_time":0.1628836511,"remaining_time":3.230525746},
{"learn":[6.431317261],"iteration":48,"passed_time":0.1635000553,"remaining_time":3.173235768},
{"learn":[6.377586395],"iteration":49,"passed_time":0.1640885573,"remaining_time":3.117682589},
{"learn":[6.327558015],"iteration":50,"passed_time":0.1647006335,"remaining_time":3.064723552},
{"learn":[6.282040317],"iteration":51,"passed_time":0.1653264554,"remaining_time":3.014028455},
{"learn":[6.237655841],"iteration":52,"passed_time":0.165954802,"remaining_time":2.965267877},
{"learn":[6.192792003],"iteration":53,"passed_time":0.1665488945,"remaining_time":2.917689892},
{"learn":[6.150579347],"iteration":54,"passed_time":0.1671403119,"remaining_time":2.87177445},
{"learn":[6.115693845],"iteration":55,"passed_time":0.1677680674,"remaining_time":2.82809028},
{"learn":[6.078780782],"iteration":56,"passed_time":0.1683676001,"remaining_time":2.785449945},
{"learn":[6.045146957],"iteration":57,"passed_time":0.1689830826,"remaining_time":2.744518342},
{"learn":[6.008080327],"iteration":58,"passed_time":0.1695773154,"remaining_time":2.70461447},
{"learn":[5.977575734],"iteration":59,"passed_time":0.1702030925,"remaining_time":2.666515115},
{"learn":[5.948036502],"iteration":60,"passed_time":0.1708748134,"remaining_time":2.630351636},
{"learn":[5.914888282],"iteration":61,"passed_time":0.1715130686,"remaining_time":2.594826748},
{"learn":[5.884957796],"iteration":62,"passed_time":0.1721307352,"remaining_time":2.560103157},
{"learn":[5.849539885],"iteration":63,"passed_time":0.1727742302,"remaining_time":2.526823117},
{"learn":[5.821387627],"iteration":64,"passed_time":0.1733857253,"remaining_time":2.494086971},
{"learn":[5.797012279],"iteration":65,"passed_time":0.1739953468,"remaining_time":2.462297787},
{"learn":[5.768685095],"iteration":66,"passed_time":0.1745966829,"remaining_time":2.431323957},
{"learn":[5.755484587],"iteration":67,"passed_time":0.1749387133,"remaining_time":2.397689424},
{"learn":[5.731887055],"iteration":68,"passed_time":0.1755220056,"remaining_time":2.368275177},
{"learn":[5.707148487],"iteration":69,"passed_time":0.1762490536,"remaining_time":2.341594569},
{"learn":[5.685365039],"iteration":70,"passed_time":0.1768454504,"remaining_time":2.313935541},
{"learn":[5.663541834],"iteration":71,"passed_time":0.1775916777,"remaining_time":2.288959402},
{"learn":[5.638108797],"iteration":72,"passed_time":0.1782405728,"remaining_time":2.26341111},
{"learn":[5.619204893],"iteration":73,"passed_time":0.1788520278,"remaining_time":2.238067267},
{"learn":[5.598472793],"iteration":74,"passed_time":0.1794542956,"remaining_time":2.213269646},
{"learn":[5.577007075],"iteration":75,"passed_time":0.180030735,"remaining_time":2.188794726},
{"learn":[5.562637084],"iteration":76,"passed_time":0.1806390141,"remaining_time":2.165322207},
{"learn":[5.54729991],"iteration":77,"passed_time":0.1812461409,"remaining_time":2.142422333},
{"learn":[5.530737623],"iteration":78,"passed_time":0.181873105,"remaining_time":2.120318097},
{"learn":[5.513704873],"iteration":79,"passed_time":0.1825027841,"remaining_time":2.098782017},
{"learn":[5.501575529],"iteration":80,"passed_time":0.1830900137,"remaining_time":2.077280526},
{"learn":[5.484080734],"iteration":81,"passed_time":0.1837100447,"remaining_time":2.056656355},
{"learn":[5.472178894],"iteration":82,"passed_time":0.1843273507,"remaining_time":2.036484103},
{"learn":[5.458923342],"iteration":83,"passed_time":0.1849399478,"remaining_time":2.016726098},
{"learn":[5.451382371],"iteration":84,"passed_time":0.185340588,"remaining_time":1.995136918},
{"learn":[5.441410748],"iteration":85,"passed_time":0.1859275472,"remaining_time":1.976020676},
{"learn":[5.434047468],"iteration":86,"passed_time":0.1863208436,"remaining_time":1.955298049},
{"learn":[5.422107497],"iteration":87,"passed_time":0.186932479,"remaining_time":1.937300236},
{"learn":[5.40731265],"iteration":88,"passed_time":0.1875250085,"remaining_time":1.919497559},
{"learn":[5.396360181],"iteration":89,"passed_time":0.1881317246,"remaining_time":1.902220771},
{"learn":[5.383793239],"iteration":90,"passed_time":0.1887263681,"remaining_time":1.885189765},
{"learn":[5.369605034],"iteration":91,"passed_time":0.1893015151,"remaining_time":1.868323649},
{"learn":[5.357467333],"iteration":92,"passed_time":0.1898818017,"remaining_time":1.851858002},
{"learn":[5.341109968],"iteration":93,"passed_time":0.1907150223,"remaining_time":1.838168194},
{"learn":[5.330529276],"iteration":94,"passed_time":0.1913521353,"remaining_time":1.822880868},
{"learn":[5.319862075],"iteration":95,"passed_time":0.1919415991,"remaining_time":1.807450059},
{"learn":[5.313052243],"iteration":96,"passed_time":0.1925148526,"remaining_time":1.792174349},
{"learn":[5.299677207],"iteration":97,"passed_time":0.1931038856,"remaining_time":1.777343927},
{"learn":[5.287546698],"iteration":98,"passed_time":0.1936949324,"remaining_time":1.762819536},
{"learn":[5.279803754],"iteration":99,"passed_time":0.194344128,"remaining_time":1.749097152},
{"learn":[5.272254612],"iteration":100,"passed_time":0.1949883444,"remaining_time":1.735589323},
{"learn":[5.268813888],"iteration":101,"passed_time":0.1953341319,"remaining_time":1.719706377},
{"learn":[5.258113767],"iteration":102,"passed_time":0.1959259801,"remaining_time":1.706268002},
{"learn":[5.251018576],"iteration":103,"passed_time":0.1965379661,"remaining_time":1.69325017},
{"learn":[5.24171237],"iteration":104,"passed_time":0.1971407248,"remaining_time":1.680389988},
{"learn":[5.233984943],"iteration":105,"passed_time":0.1977416601,"remaining_time":1.667745699},
{"learn":[5.226240449],"iteration":106,"passed_time":0.1983115172,"remaining_time":1.655067148},
{"learn":[5.220541644],"iteration":107,"passed_time":0.1989511449,"remaining_time":1.643189086},
{"learn":[5.211712096],"iteration":108,"passed_time":0.1996228427,"remaining_time":1.631779384},
{"learn":[5.203388597],"iteration":109,"passed_time":0.2008314359,"remaining_time":1.62490889},
{"learn":[5.196026544],"iteration":110,"passed_time":0.2015349332,"remaining_time":1.614095096},
{"learn":[5.188716772],"iteration":111,"passed_time":0.202148392,"remaining_time":1.602747965},
{"learn":[5.182163132],"iteration":112,"passed_time":0.202859704,"remaining_time":1.592358915},
{"learn":[5.17764747],"iteration":113,"passed_time":0.2035592439,"remaining_time":1.582048159},
{"learn":[5.170548056],"iteration":114,"passed_time":0.2042740424,"remaining_time":1.572021978},
{"learn":[5.165901827],"iteration":115,"passed_time":0.2049665992,"remaining_time":1.561986843},
{"learn":[5.160333668],"iteration":116,"passed_time":0.2056492776,"remaining_time":1.552036856},
{"learn":[5.148953243],"iteration":117,"passed_time":0.2062730156,"remaining_time":1.541803388},
{"learn":[5.144729126],"iteration":118,"passed_time":0.2067688942,"remaining_time":1.530784838},
{"learn":[5.139939946],"iteration":119,"passed_time":0.2074819093,"remaining_time":1.521534002},
{"learn":[5.132898872],"iteration":120,"passed_time":0.2081816797,"remaining_time":1.51232807},
{"learn":[5.129073077],"iteration":121,"passed_time":0.208777305,"remaining_time":1.50251208},
{"learn":[5.127123916],"iteration":122,"passed_time":0.2090898503,"remaining_time":1.490827632},
{"learn":[5.121282057],"iteration":123,"passed_time":0.2097541442,"remaining_time":1.481811535},
{"learn":[5.114489821],"iteration":124,"passed_time":0.2103336193,"remaining_time":1.472335335},
{"learn":[5.107777291],"iteration":125,"passed_time":0.211104603,"remaining_time":1.464328754},
{"learn":[5.103518754],"iteration":126,"passed_time":0.211717631,"remaining_time":1.455350329},
{"learn":[5.101133351],"iteration":127,"passed_time":0.2121791752,"remaining_time":1.445470631},
{"learn":[5.096462705],"iteration":128,"passed_time":0.2128806989,"remaining_time":1.437357277},
{"learn":[5.08562082],"iteration":129,"passed_time":0.2135532583,"remaining_time":1.429164113},
{"learn":[5.080483682],"iteration":130,"passed_time":0.2142560042,"remaining_time":1.421286013},
{"learn":[5.07437499],"iteration":131,"passed_time":0.2149785873,"remaining_time":1.413647074},
{"learn":[5.070683732],"iteration":132,"passed_time":0.2158062471,"remaining_time":1.406797115},
{"learn":[5.06432037],"iteration":133,"passed_time":0.2165631345,"remaining_time":1.39957966},
{"learn":[5.057436484],"iteration":134,"passed_time":0.2173781106,"remaining_time":1.392830116},
{"learn":[5.053254656],"iteration":135,"passed_time":0.2182787971,"remaining_time":1.386712358},
{"learn":[5.04801663],"iteration":136,"passed_time":0.2190098761,"remaining_time":1.379602358},
{"learn":[5.045680836],"iteration":137,"passed_time":0.219560908,"remaining_time":1.371460164},
{"learn":[5.041857933],"iteration":138,"passed_time":0.220251401,"remaining_time":1.364291052},
{"learn":[5.035264888],"iteration":139,"passed_time":0.2209166968,"remaining_time":1.357059709},
{"learn":[5.028771948],"iteration":140,"passed_time":0.2216183106,"remaining_time":1.350142757},
{"learn":[5.024912247],"iteration":141,"passed_time":0.2223524854,"remaining_time":1.343510088},
{"learn":[5.02239068],"iteration":142,"passed_time":0.2230691373,"remaining_time":1.3368549},
{"learn":[5.017110572],"iteration":143,"passed_time":0.2238735236,"remaining_time":1.330803724},
{"learn":[5.010707886],"iteration":144,"passed_time":0.2245805676,"remaining_time":1.324250933},
{"learn":[5.004389868],"iteration":145,"passed_time":0.225321495,"remaining_time":1.317976416},
{"learn":[4.997628683],"iteration":146,"passed_time":0.2259504227,"remaining_time":1.311127283},
{"learn":[4.991497851],"iteration":147,"passed_time":0.2266269095,"remaining_time":1.304635992},
{"learn":[4.988345253],"iteration":148,"passed_time":0.2273905795,"remaining_time":1.298720692},
{"learn":[4.98460423],"iteration":149,"passed_time":0.2281038051,"remaining_time":1.292588229},
{"learn":[4.982441783],"iteration":150,"passed_time":0.2287213014,"remaining_time":1.285989304},
{"learn":[4.977461771],"iteration":151,"passed_time":0.2294520798,"remaining_time":1.280101077},
{"learn":[4.973601586],"iteration":152,"passed_time":0.2300863776,"remaining_time":1.273746155},
{"learn":[4.968328804],"iteration":153,"passed_time":0.2308383056,"remaining_time":1.268111731},
{"learn":[4.9640736],"iteration":154,"passed_time":0.2317641092,"remaining_time":1.263488208},
{"learn":[4.960865882],"iteration":155,"passed_time":0.232541014,"remaining_time":1.258106512},
{"learn":[4.957014156],"iteration":156,"passed_time":0.2333147028,"remaining_time":1.252766207},
{"learn":[4.952244852],"iteration":157,"passed_time":0.2339186437,"remaining_time":1.246579101},
{"learn":[4.949695675],"iteration":158,"passed_time":0.2345751531,"remaining_time":1.240740275},
{"learn":[4.946584698],"iteration":159,"passed_time":0.2352273343,"remaining_time":1.234943505},
{"learn":[4.940192834],"iteration":160,"passed_time":0.2359170058,"remaining_time":1.229406011},
{"learn":[4.936727994],"iteration":161,"passed_time":0.2367317214,"remaining_time":1.224575201},
{"learn":[4.932342063],"iteration":162,"passed_time":0.2374852324,"remaining_time":1.219479383},
{"learn":[4.925830838],"iteration":163,"passed_time":0.2382170327,"remaining_time":1.21432585},
{"learn":[4.922571773],"iteration":164,"passed_time":0.2389062333,"remaining_time":1.209010332},
{"learn":[4.918395814],"iteration":165,"passed_time":0.2396410593,"remaining_time":1.20397978},
{"learn":[4.911142452],"iteration":166,"passed_time":0.2403435447,"remaining_time":1.198839358},
{"learn":[4.908276131],"iteration":167,"passed_time":0.2410134492,"remaining_time":1.193590415},
{"learn":[4.904584645],"iteration":168,"passed_time":0.2416143844,"remaining_time":1.188056529},
{"learn":[4.89795517],"iteration":169,"passed_time":0.242309476,"remaining_time":1.183040383},
{"learn":[4.895556491],"iteration":170,"passed_time":0.2430793677,"remaining_time":1.178437403},
{"learn":[4.890591233],"iteration":171,"passed_time":0.2438267773,"remaining_time":1.173770765},
{"learn":[4.884629277],"iteration":172,"passed_time":0.2444422899,"remaining_time":1.168518923},
{"learn":[4.880550786],"iteration":173,"passed_time":0.2452415966,"remaining_time":1.164192867},
{"learn":[4.876384842],"iteration":174,"passed_time":0.2461297397,"remaining_time":1.160325916},
{"learn":[4.872638238],"iteration":175,"passed_time":0.2469707846,"remaining_time":1.15627231},
{"learn":[4.869137118],"iteration":176,"passed_time":0.2476945599,"remaining_time":1.151709734},
{"learn":[4.863587157],"iteration":177,"passed_time":0.2484375212,"remaining_time":1.14727889},
{"learn":[4.858028614],"iteration":178,"passed_time":0.2490430551,"remaining_time":1.142258929},
{"learn":[4.853838176],"iteration":179,"passed_time":0.2497019689,"remaining_time":1.137531192},
{"learn":[4.853462329],"iteration":180,"passed_time":0.250136152,"remaining_time":1.131831538},
{"learn":[4.851573196],"iteration":181,"passed_time":0.2509359797,"remaining_time":1.12783314},
{"learn":[4.848442087],"iteration":182,"passed_time":0.2515980695,"remaining_time":1.123254769},
{"learn":[4.845547104],"iteration":183,"passed_time":0.2522110674,"remaining_time":1.118501255},
{"learn":[4.839868817],"iteration":184,"passed_time":0.2529962276,"remaining_time":1.114550949},
{"learn":[4.836336958],"iteration":185,"passed_time":0.2536874019,"remaining_time":1.110223361},
{"learn":[4.831124789],"iteration":186,"passed_time":0.2544520337,"remaining_time":1.106254029},
{"learn":[4.827407333],"iteration":187,"passed_time":0.2551406231,"remaining_time":1.101990351},
{"learn":[4.824088918],"iteration":188,"passed_time":0.255897781,"remaining_time":1.098058732},
{"learn":[4.820934539],"iteration":189,"passed_time":0.2565482089,"remaining_time":1.093705522},
{"learn":[4.816975227],"iteration":190,"passed_time":0.2573018602,"remaining_time":1.089828298},
{"learn":[4.812340486],"iteration":191,"passed_time":0.2579814027,"remaining_time":1.085671736},
{"learn":[4.806402747],"iteration":192,"passed_time":0.2586090981,"remaining_time":1.081334415},
{"learn":[4.801521788],"iteration":193,"passed_time":0.2593299179,"remaining_time":1.077422236},
{"learn":[4.797601172],"iteration":194,"passed_time":0.2600835591,"remaining_time":1.073678282},
{"learn":[4.792694629],"iteration":195,"passed_time":0.2609522057,"remaining_time":1.070436599},
{"learn":[4.789794613],"iteration":196,"passed_time":0.2618501471,"remaining_time":1.067338417},
{"learn":[4.785367055],"iteration":197,"passed_time":0.2626624282,"remaining_time":1.063915492},
{"learn":[4.780376856],"iteration":198,"passed_time":0.2634480493,"remaining_time":1.060411495},
{"learn":[4.776691261],"iteration":199,"passed_time":0.2642761199,"remaining_time":1.05710448},
{"learn":[4.773470753],"iteration":200,"passed_time":0.26505584,"remaining_time":1.053629931},
{"learn":[4.77207327],"iteration":201,"passed_time":0.2659746205,"remaining_time":1.050731421},
{"learn":[4.767347177],"iteration":202,"passed_time":0.2666713451,"remaining_time":1.046980601},
{"learn":[4.763983068],"iteration":203,"passed_time":0.2674951878,"remaining_time":1.043755733},
{"learn":[4.761588849],"iteration":204,"passed_time":0.268328879,"remaining_time":1.040592482},
{"learn":[4.758558086],"iteration":205,"passed_time":0.2691825575,"remaining_time":1.037528887},
{"learn":[4.753678804],"iteration":206,"passed_time":0.2700017415,"remaining_time":1.034354498},
{"learn":[4.746510889],"iteration":207,"passed_time":0.2710797201,"remaining_time":1.032188165},
{"learn":[4.744840601],"iteration":208,"passed_time":0.2718757407,"remaining_time":1.028965124},
{"learn":[4.741702222],"iteration":209,"passed_time":0.272601109,"remaining_time":1.02549941},
{"learn":[4.739352853],"iteration":210,"passed_time":0.2733016007,"remaining_time":1.021966649},
{"learn":[4.735539287],"iteration":211,"passed_time":0.2741636549,"remaining_time":1.019061132},
{"learn":[4.730726751],"iteration":212,"passed_time":0.2749876479,"remaining_time":1.016034173},
{"learn":[4.726416092],"iteration":213,"passed_time":0.2757322622,"remaining_time":1.012736253},
{"learn":[4.721293082],"iteration":214,"passed_time":0.2766291718,"remaining_time":1.010018139},
{"learn":[4.718443695],"iteration":215,"passed_time":0.277523787,"remaining_time":1.00730856},
{"learn":[4.711627962],"iteration":216,"passed_time":0.2783924135,"remaining_time":1.004521935},
{"learn":[4.709790764],"iteration":217,"passed_time":0.2793475821,"remaining_time":1.002063345},
{"learn":[4.706913073],"iteration":218,"passed_time":0.2801859621,"remaining_time":0.9992019925},
{"learn":[4.703846389],"iteration":219,"passed_time":0.2811693836,"remaining_time":0.996873269},
{"learn":[4.701001135],"iteration":220,"passed_time":0.2821449905,"remaining_time":0.9945291745},
{"learn":[4.700380864],"iteration":221,"passed_time":0.2830434128,"remaining_time":0.9919269152},
{"learn":[4.695837486],"iteration":222,"passed_time":0.2839214871,"remaining_time":0.9892690379},
{"learn":[4.691242996],"iteration":223,"passed_time":0.2850255545,"remaining_time":0.9874099566},
{"learn":[4.690284609],"iteration":224,"passed_time":0.2857689866,"remaining_time":0.9843153983},
{"learn":[4.68827119],"iteration":225,"passed_time":0.2865142021,"remaining_time":0.981247754},
{"learn":[4.686922425],"iteration":226,"passed_time":0.2871473276,"remaining_time":0.9778188734},
{"learn":[4.686085874],"iteration":227,"passed_time":0.2877661865,"remaining_time":0.9743662104},
{"learn":[4.683230741],"iteration":228,"passed_time":0.2883761487,"remaining_time":0.9709083434},
{"learn":[4.6773487],"iteration":229,"passed_time":0.2890285103,"remaining_time":0.9676171865},
{"learn":[4.671462906],"iteration":230,"passed_time":0.2896634893,"remaining_time":0.9642910098},
{"learn":[4.664799601],"iteration":231,"passed_time":0.2903051208,"remaining_time":0.961010055},
{"learn":[4.660979386],"iteration":232,"passed_time":0.2909455601,"remaining_time":0.9577478307},
{"learn":[4.656281279],"iteration":233,"passed_time":0.2915919705,"remaining_time":0.9545275616},
{"learn":[4.651997094],"iteration":234,"passed_time":0.2922174117,"remaining_time":0.9512609359},
{"learn":[4.650151977],"iteration":235,"passed_time":0.2928422718,"remaining_time":0.948014812},
{"learn":[4.648478046],"iteration":236,"passed_time":0.2934652583,"remaining_time":0.9447847769},
{"learn":[4.646364602],"iteration":237,"passed_time":0.2944048778,"remaining_time":0.9425904072},
{"learn":[4.642635873],"iteration":238,"passed_time":0.2951970613,"remaining_time":0.9399370862},
{"learn":[4.640860821],"iteration":239,"passed_time":0.2959633361,"remaining_time":0.9372172311},
{"learn":[4.639446822],"iteration":240,"passed_time":0.29673441,"remaining_time":0.9345287021},
{"learn":[4.637120072],"iteration":241,"passed_time":0.2974561415,"remaining_time":0.9317014681},
{"learn":[4.633769267],"iteration":242,"passed_time":0.2981021913,"remaining_time":0.9286557975},
{"learn":[4.630491517],"iteration":243,"passed_time":0.2986223653,"remaining_time":0.9252397877},
{"learn":[4.627813333],"iteration":244,"passed_time":0.2991405958,"remaining_time":0.9218414277},
{"learn":[4.622496304],"iteration":245,"passed_time":0.2996861473,"remaining_time":0.9185502239},
{"learn":[4.618979301],"iteration":246,"passed_time":0.3001998994,"remaining_time":0.9151843086},
{"learn":[4.616563458],"iteration":247,"passed_time":0.3007093233,"remaining_time":0.9118282706},
{"learn":[4.614759385],"iteration":248,"passed_time":0.3012104016,"remaining_time":0.9084699261},
{"learn":[4.61251363],"iteration":249,"passed_time":0.3017049076,"remaining_time":0.9051147228},
{"learn":[4.608796693],"iteration":250,"passed_time":0.3022742136,"remaining_time":0.902005522},
{"learn":[4.60847774],"iteration":251,"passed_time":0.3028456337,"remaining_time":0.8989227539},
{"learn":[4.605195659],"iteration":252,"passed_time":0.3033710475,"remaining_time":0.895724002},
{"learn":[4.60103766],"iteration":253,"passed_time":0.3038918227,"remaining_time":0.8925326762},
{"learn":[4.599325598],"iteration":254,"passed_time":0.3043754483,"remaining_time":0.8892537608},
{"learn":[4.597012808],"iteration":255,"passed_time":0.3048648648,"remaining_time":0.8860135133},
{"learn":[4.594161533],"iteration":256,"passed_time":0.3056023758,"remaining_time":0.883511927},
{"learn":[4.592197259],"iteration":257,"passed_time":0.3061606713,"remaining_time":0.8805085972},
{"learn":[4.58952828],"iteration":258,"passed_time":0.3066654766,"remaining_time":0.8773711125},
{"learn":[4.585816572],"iteration":259,"passed_time":0.3071494328,"remaining_time":0.8741945395},
{"learn":[4.582934052],"iteration":260,"passed_time":0.3076389194,"remaining_time":0.8710542583},
{"learn":[4.582234842],"iteration":261,"passed_time":0.3081441154,"remaining_time":0.8679784624},
{"learn":[4.57571562],"iteration":262,"passed_time":0.3086383108,"remaining_time":0.8648913881},
{"learn":[4.571197349],"iteration":263,"passed_time":0.3091433766,"remaining_time":0.861854262},
{"learn":[4.56723703],"iteration":264,"passed_time":0.3096241969,"remaining_time":0.858768999},
{"learn":[4.560335567],"iteration":265,"passed_time":0.3101408444,"remaining_time":0.8558021796},
{"learn":[4.554709345],"iteration":266,"passed_time":0.3106467618,"remaining_time":0.852824256},
{"learn":[4.552806306],"iteration":267,"passed_time":0.3112853976,"remaining_time":0.8502272801},
{"learn":[4.550766241],"iteration":268,"passed_time":0.3119439909,"remaining_time":0.8476990979},
{"learn":[4.549216045],"iteration":269,"passed_time":0.3125707846,"remaining_time":0.845098788},
{"learn":[4.547687452],"iteration":270,"passed_time":0.3132257811,"remaining_time":0.8425889094},
{"learn":[4.545642435],"iteration":271,"passed_time":0.3138568428,"remaining_time":0.8400286087},
{"learn":[4.543930359],"iteration":272,"passed_time":0.3144680273,"remaining_time":0.8374295086},
{"learn":[4.541029943],"iteration":273,"passed_time":0.3150997302,"remaining_time":0.8348992851},
{"learn":[4.537781449],"iteration":274,"passed_time":0.3156931232,"remaining_time":0.8322818704},
{"learn":[4.53066128],"iteration":275,"passed_time":0.3163422187,"remaining_time":0.8298252404},
{"learn":[4.526763956],"iteration":276,"passed_time":0.317032351,"remaining_time":0.8274887718},
{"learn":[4.522036004],"iteration":277,"passed_time":0.3177365797,"remaining_time":0.8252007575},
{"learn":[4.515307629],"iteration":278,"passed_time":0.3183772995,"remaining_time":0.8227599748},
{"learn":[4.51109143],"iteration":279,"passed_time":0.3189734659,"remaining_time":0.8202174837},
{"learn":[4.508233494],"iteration":280,"passed_time":0.3195755333,"remaining_time":0.8177039446},
{"learn":[4.502555629],"iteration":281,"passed_time":0.3202383144,"remaining_time":0.8153585451},
{"learn":[4.500081355],"iteration":282,"passed_time":0.3208280988,"remaining_time":0.8128400948},
{"learn":[4.495281743],"iteration":283,"passed_time":0.3213561777,"remaining_time":0.8101796592},
{"learn":[4.492138869],"iteration":284,"passed_time":0.3218780248,"remaining_time":0.8075185536},
{"learn":[4.491708261],"iteration":285,"passed_time":0.3224387048,"remaining_time":0.8049693538},
{"learn":[4.489398865],"iteration":286,"passed_time":0.3229990039,"remaining_time":0.8024330656},
{"learn":[4.485796373],"iteration":287,"passed_time":0.3236321395,"remaining_time":0.8000905672},
{"learn":[4.479542205],"iteration":288,"passed_time":0.3242156422,"remaining_time":0.797637791},
{"learn":[4.475986993],"iteration":289,"passed_time":0.3247742682,"remaining_time":0.7951370015},
{"learn":[4.468661855],"iteration":290,"passed_time":0.3253347277,"remaining_time":0.7926540274},
{"learn":[4.463785664],"iteration":291,"passed_time":0.3258435906,"remaining_time":0.790059117},
{"learn":[4.460445831],"iteration":292,"passed_time":0.3263894928,"remaining_time":0.7875678206},
{"learn":[4.45692492],"iteration":293,"passed_time":0.3269038961,"remaining_time":0.7850141178},
{"learn":[4.454031688],"iteration":294,"passed_time":0.3274300013,"remaining_time":0.7825022064},
{"learn":[4.451672391],"iteration":295,"passed_time":0.3280118308,"remaining_time":0.7801362462},
{"learn":[4.45031553],"iteration":296,"passed_time":0.3285765583,"remaining_time":0.7777418197},
{"learn":[4.446782666],"iteration":297,"passed_time":0.3291470065,"remaining_time":0.7753731494},
{"learn":[4.444369689],"iteration":298,"passed_time":0.3303308433,"remaining_time":0.7744545857},
{"learn":[4.44411683],"iteration":299,"passed_time":0.3309178825,"remaining_time":0.7721417259},
{"learn":[4.440876943],"iteration":300,"passed_time":0.3314723057,"remaining_time":0.7697645904},
{"learn":[4.439336453],"iteration":301,"passed_time":0.3319795255,"remaining_time":0.7672904265},
{"learn":[4.436666901],"iteration":302,"passed_time":0.3324916946,"remaining_time":0.7648406308},
{"learn":[4.433043336],"iteration":303,"passed_time":0.3329963396,"remaining_time":0.7623863564},
{"learn":[4.431419305],"iteration":304,"passed_time":0.3335066752,"remaining_time":0.7599578336},
{"learn":[4.428859646],"iteration":305,"passed_time":0.3340194254,"remaining_time":0.7575473242},
{"learn":[4.424552441],"iteration":306,"passed_time":0.334539399,"remaining_time":0.7551654838},
{"learn":[4.422706391],"iteration":307,"passed_time":0.3350510772,"remaining_time":0.7527770955},
{"learn":[4.421427994],"iteration":308,"passed_time":0.3355541492,"remaining_time":0.7503816088},
{"learn":[4.418733158],"iteration":309,"passed_time":0.3360633127,"remaining_time":0.7480118895},
{"learn":[4.415656941],"iteration":310,"passed_time":0.3365740791,"remaining_time":0.7456576865},
{"learn":[4.410747417],"iteration":311,"passed_time":0.3370942031,"remaining_time":0.743335935},
{"learn":[4.408126521],"iteration":312,"passed_time":0.3376087867,"remaining_time":0.7410135349},
{"learn":[4.407843853],"iteration":313,"passed_time":0.3380978725,"remaining_time":0.7386469444},
{"learn":[4.405219398],"iteration":314,"passed_time":0.3386139188,"remaining_time":0.7363509028},
{"learn":[4.402708465],"iteration":315,"passed_time":0.339125076,"remaining_time":0.7340555442},
{"learn":[4.40104971],"iteration":316,"passed_time":0.3396518825,"remaining_time":0.73180516},
{"learn":[4.400830038],"iteration":317,"passed_time":0.3401331837,"remaining_time":0.729468023},
{"learn":[4.39784288],"iteration":318,"passed_time":0.340634242,"remaining_time":0.7271846984},
{"learn":[4.393741845],"iteration":319,"passed_time":0.34115117,"remaining_time":0.7249462362},
{"learn":[4.393425936],"iteration":320,"passed_time":0.3416538713,"remaining_time":0.7226884069},
{"learn":[4.390505974],"iteration":321,"passed_time":0.3421544988,"remaining_time":0.7204371123},
{"learn":[4.390305136],"iteration":322,"passed_time":0.3426355896,"remaining_time":0.7181557096},
{"learn":[4.38568203],"iteration":323,"passed_time":0.3431509747,"remaining_time":0.715956972},
{"learn":[4.383057135],"iteration":324,"passed_time":0.3436581745,"remaining_time":0.7137515932},
{"learn":[4.380662684],"iteration":325,"passed_time":0.3441791701,"remaining_time":0.7115851553},
{"learn":[4.37805727],"iteration":326,"passed_time":0.3446792966,"remaining_time":0.7093858306},
{"learn":[4.373708319],"iteration":327,"passed_time":0.3451924876,"remaining_time":0.7072236331},
{"learn":[4.36887921],"iteration":328,"passed_time":0.3457280104,"remaining_time":0.705117006},
{"learn":[4.367895929],"iteration":329,"passed_time":0.3464060801,"remaining_time":0.7033093142},
{"learn":[4.362140573],"iteration":330,"passed_time":0.3469654576,"remaining_time":0.7012685532},
{"learn":[4.361931924],"iteration":331,"passed_time":0.3474664758,"remaining_time":0.6991192946},
{"learn":[4.359656377],"iteration":332,"passed_time":0.3479731846,"remaining_time":0.6969913337},
{"learn":[4.354281355],"iteration":333,"passed_time":0.3484859548,"remaining_time":0.6948851674},
{"learn":[4.348589447],"iteration":334,"passed_time":0.3490107375,"remaining_time":0.6928123595},
{"learn":[4.346355698],"iteration":335,"passed_time":0.3495388464,"remaining_time":0.6907553393},
{"learn":[4.343894047],"iteration":336,"passed_time":0.350049132,"remaining_time":0.6886723278},
{"learn":[4.341561356],"iteration":337,"passed_time":0.3506403891,"remaining_time":0.6867572118},
{"learn":[4.338869061],"iteration":338,"passed_time":0.351162627,"remaining_time":0.6847153288},
{"learn":[4.333720063],"iteration":339,"passed_time":0.3516787134,"remaining_time":0.6826704437},
{"learn":[4.330892223],"iteration":340,"passed_time":0.352194359,"remaining_time":0.6806336733},
{"learn":[4.328311474],"iteration":341,"passed_time":0.3527185406,"remaining_time":0.6786222213},
{"learn":[4.324580133],"iteration":342,"passed_time":0.3532381335,"remaining_time":0.6766106523},
{"learn":[4.323354432],"iteration":343,"passed_time":0.3537624854,"remaining_time":0.6746168327},
{"learn":[4.323159553],"iteration":344,"passed_time":0.3542563502,"remaining_time":0.6725736504},
{"learn":[4.318639682],"iteration":345,"passed_time":0.3547782776,"remaining_time":0.6705924668},
{"learn":[4.312712208],"iteration":346,"passed_time":0.3552903665,"remaining_time":0.6686011796},
{"learn":[4.311461062],"iteration":347,"passed_time":0.3557980772,"remaining_time":0.6666101906},
{"learn":[4.311178356],"iteration":348,"passed_time":0.3562865619,"remaining_time":0.664591839},
{"learn":[4.311102505],"iteration":349,"passed_time":0.3567685645,"remaining_time":0.6625701912},
{"learn":[4.310232308],"iteration":350,"passed_time":0.3572677793,"remaining_time":0.6605891418},
{"learn":[4.305128197],"iteration":351,"passed_time":0.3577864005,"remaining_time":0.6586522372},
{"learn":[4.304595496],"iteration":352,"passed_time":0.3582844731,"remaining_time":0.6566857057},
{"learn":[4.3004992],"iteration":353,"passed_time":0.3587989365,"remaining_time":0.6547573813},
{"learn":[4.297581524],"iteration":354,"passed_time":0.3593026297,"remaining_time":0.6528174539},
{"learn":[4.297355825],"iteration":355,"passed_time":0.3597910142,"remaining_time":0.6508579021},
{"learn":[4.295758715],"iteration":356,"passed_time":0.3602871132,"remaining_time":0.6489204868},
{"learn":[4.292500657],"iteration":357,"passed_time":0.3607984707,"remaining_time":0.6470184866},
{"learn":[4.290797586],"iteration":358,"passed_time":0.3613020337,"remaining_time":0.6451103164},
{"learn":[4.286410608],"iteration":359,"passed_time":0.3618775213,"remaining_time":0.6433378157},
{"learn":[4.280278245],"iteration":360,"passed_time":0.3624112508,"remaining_time":0.6414980311},
{"learn":[4.279941283],"iteration":361,"passed_time":0.3629146534,"remaining_time":0.6396120135},
{"learn":[4.274426275],"iteration":362,"passed_time":0.3634414399,"remaining_time":0.6377746479},
{"learn":[4.273567658],"iteration":363,"passed_time":0.3639463553,"remaining_time":0.6359062692},
{"learn":[4.269488271],"iteration":364,"passed_time":0.3644630629,"remaining_time":0.6340658766},
{"learn":[4.266838205],"iteration":365,"passed_time":0.3649693009,"remaining_time":0.6322145813},
{"learn":[4.263456509],"iteration":366,"passed_time":0.3654832533,"remaining_time":0.6303839219},
{"learn":[4.260360204],"iteration":367,"passed_time":0.3659961938,"remaining_time":0.6285586806},
{"learn":[4.255120549],"iteration":368,"passed_time":0.3665024518,"remaining_time":0.6267291249},
{"learn":[4.252582211],"iteration":369,"passed_time":0.367013108,"remaining_time":0.624914211},
{"learn":[4.247857931],"iteration":370,"passed_time":0.3675437717,"remaining_time":0.6231402491},
{"learn":[4.245288911],"iteration":371,"passed_time":0.3680519734,"remaining_time":0.6213350518},
{"learn":[4.24048515],"iteration":372,"passed_time":0.3685665369,"remaining_time":0.6195475031},
{"learn":[4.2378365],"iteration":373,"passed_time":0.3690700097,"remaining_time":0.617748198},
{"learn":[4.236751063],"iteration":374,"passed_time":0.3695784518,"remaining_time":0.6159640863},
{"learn":[4.233240093],"iteration":375,"passed_time":0.3701239733,"remaining_time":0.6142482961},
{"learn":[4.230358421],"iteration":376,"passed_time":0.3706579632,"remaining_time":0.6125196581},
{"learn":[4.225853583],"iteration":377,"passed_time":0.3711876351,"remaining_time":0.6107902355},
{"learn":[4.224702126],"iteration":378,"passed_time":0.3716855274,"remaining_time":0.6090150726},
{"learn":[4.224361982],"iteration":379,"passed_time":0.372176607,"remaining_time":0.6072355167},
{"learn":[4.223787954],"iteration":380,"passed_time":0.3726670654,"remaining_time":0.6054617152},
{"learn":[4.22144054],"iteration":381,"passed_time":0.3731720911,"remaining_time":0.6037181997},
{"learn":[4.217739335],"iteration":382,"passed_time":0.3736901812,"remaining_time":0.602002198},
{"learn":[4.215611665],"iteration":383,"passed_time":0.3741832646,"remaining_time":0.6002523203},
{"learn":[4.210236863],"iteration":384,"passed_time":0.374694532,"remaining_time":0.5985380186},
{"learn":[4.208454294],"iteration":385,"passed_time":0.3752027436,"remaining_time":0.5968250896},
{"learn":[4.207446501],"iteration":386,"passed_time":0.3756961876,"remaining_time":0.5950949949},
{"learn":[4.204985442],"iteration":387,"passed_time":0.3762123241,"remaining_time":0.5934070679},
{"learn":[4.202796622],"iteration":388,"passed_time":0.3767182014,"remaining_time":0.5917090516},
{"learn":[4.199774004],"iteration":389,"passed_time":0.3772341776,"remaining_time":0.5900329444},
{"learn":[4.199458358],"iteration":390,"passed_time":0.3777508751,"remaining_time":0.588363895},
{"learn":[4.19751254],"iteration":391,"passed_time":0.3782663805,"remaining_time":0.5866988758},
{"learn":[4.195201346],"iteration":392,"passed_time":0.3787687612,"remaining_time":0.5850194352},
{"learn":[4.190593508],"iteration":393,"passed_time":0.3792824732,"remaining_time":0.5833633978},
{"learn":[4.187212054],"iteration":394,"passed_time":0.3797841025,"remaining_time":0.581694638},
{"learn":[4.184984466],"iteration":395,"passed_time":0.3802930956,"remaining_time":0.5800430044},
{"learn":[4.182832144],"iteration":396,"passed_time":0.3807967187,"remaining_time":0.5783889707},
{"learn":[4.179752812],"iteration":397,"passed_time":0.3813094187,"remaining_time":0.5767544474},
{"learn":[4.17878934],"iteration":398,"passed_time":0.3818132923,"remaining_time":0.5751122523},
{"learn":[4.174548229],"iteration":399,"passed_time":0.3823328351,"remaining_time":0.5734992527},
{"learn":[4.168872556],"iteration":400,"passed_time":0.3828369992,"remaining_time":0.5718687345},
{"learn":[4.163926494],"iteration":401,"passed_time":0.3833444895,"remaining_time":0.570248768},
{"learn":[4.159485076],"iteration":402,"passed_time":0.383851519,"remaining_time":0.5686336398},
{"learn":[4.155926102],"iteration":403,"passed_time":0.3843579172,"remaining_time":0.567023066},
{"learn":[4.153540115],"iteration":404,"passed_time":0.3849803929,"remaining_time":0.5655884784},
{"learn":[4.150983044],"iteration":405,"passed_time":0.3855978491,"remaining_time":0.5641505477},
{"learn":[4.146539132],"iteration":406,"passed_time":0.3861324101,"remaining_time":0.5625958702},
{"learn":[4.144869174],"iteration":407,"passed_time":0.3866407219,"remaining_time":0.5610081063},
{"learn":[4.142825962],"iteration":408,"passed_time":0.3871591327,"remaining_time":0.5594402137},
{"learn":[4.142467378],"iteration":409,"passed_time":0.3876555222,"remaining_time":0.5578457514},
{"learn":[4.141800768],"iteration":410,"passed_time":0.3881468222,"remaining_time":0.5562493388},
{"learn":[4.140107084],"iteration":411,"passed_time":0.3886479806,"remaining_time":0.5546723607},
{"learn":[4.136243196],"iteration":412,"passed_time":0.3891683551,"remaining_time":0.5531279042},
{"learn":[4.133618439],"iteration":413,"passed_time":0.3897464877,"remaining_time":0.5516701492},
{"learn":[4.131053025],"iteration":414,"passed_time":0.3902713405,"remaining_time":0.5501415281},
{"learn":[4.128379975],"iteration":415,"passed_time":0.3907983974,"remaining_time":0.5486208271},
{"learn":[4.127068571],"iteration":416,"passed_time":0.391309264,"remaining_time":0.5470822564},
{"learn":[4.125969877],"iteration":417,"passed_time":0.3918154619,"remaining_time":0.5455421025},
{"learn":[4.123893633],"iteration":418,"passed_time":0.3923390624,"remaining_time":0.5440310149},
{"learn":[4.119643722],"iteration":419,"passed_time":0.3931512032,"remaining_time":0.5429230901},
{"learn":[4.11465686],"iteration":420,"passed_time":0.3936657367,"remaining_time":0.5414072721},
{"learn":[4.111565986],"iteration":421,"passed_time":0.3941696403,"remaining_time":0.53988164},
{"learn":[4.106322452],"iteration":422,"passed_time":0.3946813585,"remaining_time":0.5383714985},
{"learn":[4.104222175],"iteration":423,"passed_time":0.395192676,"remaining_time":0.5368655221},
{"learn":[4.103008002],"iteration":424,"passed_time":0.3956837055,"remaining_time":0.535336778},
{"learn":[4.099176337],"iteration":425,"passed_time":0.396201445,"remaining_time":0.5338488953},
{"learn":[4.096525716],"iteration":426,"passed_time":0.3967116403,"remaining_time":0.532355433},
{"learn":[4.094967724],"iteration":427,"passed_time":0.3972295501,"remaining_time":0.5308768754},
{"learn":[4.094683584],"iteration":428,"passed_time":0.397717584,"remaining_time":0.5293630314},
{"learn":[4.091096563],"iteration":429,"passed_time":0.3982122102,"remaining_time":0.5278626973},
{"learn":[4.089178677],"iteration":430,"passed_time":0.3987161038,"remaining_time":0.5263792646},
{"learn":[4.085335077],"iteration":431,"passed_time":0.3992424294,"remaining_time":0.5249298609},
{"learn":[4.084852122],"iteration":432,"passed_time":0.3997598483,"remaining_time":0.5234730577},
{"learn":[4.080322952],"iteration":433,"passed_time":0.400280383,"remaining_time":0.522024647},
{"learn":[4.077449519],"iteration":434,"passed_time":0.4007950267,"remaining_time":0.5205728508},
{"learn":[4.076568374],"iteration":435,"passed_time":0.401292338,"remaining_time":0.5191029326},
{"learn":[4.076071793],"iteration":436,"passed_time":0.4017944282,"remaining_time":0.5176436225},
{"learn":[4.075027644],"iteration":437,"passed_time":0.4023079297,"remaining_time":0.5162033253},
{"learn":[4.07020837],"iteration":438,"passed_time":0.4028146586,"remaining_time":0.5147585956},
{"learn":[4.06833694],"iteration":439,"passed_time":0.4033215778,"remaining_time":0.5133183718},
{"learn":[4.063936568],"iteration":440,"passed_time":0.4038415716,"remaining_time":0.5118989535},
{"learn":[4.061734926],"iteration":441,"passed_time":0.4043527888,"remaining_time":0.5104725253},
{"learn":[4.060815619],"iteration":442,"passed_time":0.4048664407,"remaining_time":0.50905329},
{"learn":[4.056407489],"iteration":443,"passed_time":0.4053911833,"remaining_time":0.5076520223},
{"learn":[4.05238936],"iteration":444,"passed_time":0.405901539,"remaining_time":0.5062367508},
{"learn":[4.049685254],"iteration":445,"passed_time":0.4064285258,"remaining_time":0.5048461957},
{"learn":[4.045162016],"iteration":446,"passed_time":0.4069457042,"remaining_time":0.5034473701},
{"learn":[4.042955482],"iteration":447,"passed_time":0.4074548977,"remaining_time":0.5020426418},
{"learn":[4.041467663],"iteration":448,"passed_time":0.4079643217,"remaining_time":0.5006421854},
{"learn":[4.038920476],"iteration":449,"passed_time":0.4084760399,"remaining_time":0.4992484932},
{"learn":[4.036694383],"iteration":450,"passed_time":0.4089895314,"remaining_time":0.4978608708},
{"learn":[4.034999007],"iteration":451,"passed_time":0.4096208035,"remaining_time":0.4966199122},
{"learn":[4.031928018],"iteration":452,"passed_time":0.4101330828,"remaining_time":0.4952379609},
{"learn":[4.028718143],"iteration":453,"passed_time":0.410648508,"remaining_time":0.4938636241},
{"learn":[4.027401978],"iteration":454,"passed_time":0.411148394,"remaining_time":0.49247445},
{"learn":[4.025930598],"iteration":455,"passed_time":0.4116528086,"remaining_time":0.4910945786},
{"learn":[4.021074523],"iteration":456,"passed_time":0.4121632744,"remaining_time":0.4897257287},
{"learn":[4.020268486],"iteration":457,"passed_time":0.4126558067,"remaining_time":0.4883394045},
{"learn":[4.017986361],"iteration":458,"passed_time":0.4131591693,"remaining_time":0.4869697399},
{"learn":[4.014814804],"iteration":459,"passed_time":0.413730399,"remaining_time":0.4856835118},
{"learn":[4.009704796],"iteration":460,"passed_time":0.4142521961,"remaining_time":0.4843425893},
{"learn":[4.008440457],"iteration":461,"passed_time":0.4147758767,"remaining_time":0.4830074062},
{"learn":[4.004854849],"iteration":462,"passed_time":0.4153034346,"remaining_time":0.4816802254},
{"learn":[4.000898028],"iteration":463,"passed_time":0.4158239994,"remaining_time":0.4803484131},
{"learn":[3.996617985],"iteration":464,"passed_time":0.4163349662,"remaining_time":0.4790090471},
{"learn":[3.995443319],"iteration":465,"passed_time":0.4168486581,"remaining_time":0.4776763593},
{"learn":[3.990771995],"iteration":466,"passed_time":0.4173656562,"remaining_time":0.4763509524},
{"learn":[3.989249359],"iteration":467,"passed_time":0.4178769136,"remaining_time":0.4750224744},
{"learn":[3.986599538],"iteration":468,"passed_time":0.4183859267,"remaining_time":0.4736949405},
{"learn":[3.985628919],"iteration":469,"passed_time":0.4189002398,"remaining_time":0.4723768662},
{"learn":[3.985086112],"iteration":470,"passed_time":0.4193922712,"remaining_time":0.4710371793},
{"learn":[3.98466839],"iteration":471,"passed_time":0.4198986494,"remaining_time":0.4697171332},
{"learn":[3.984233894],"iteration":472,"passed_time":0.4204138742,"remaining_time":0.4684103841},
{"learn":[3.981855845],"iteration":473,"passed_time":0.420929129,"remaining_time":0.4671070082},
{"learn":[3.978684264],"iteration":474,"passed_time":0.4214431716,"remaining_time":0.4658056107},
{"learn":[3.974361269],"iteration":475,"passed_time":0.4219617727,"remaining_time":0.4645125397},
{"learn":[3.972074049],"iteration":476,"passed_time":0.4224775786,"remaining_time":0.4632196512},
{"learn":[3.97191982],"iteration":477,"passed_time":0.42296962,"remaining_time":0.461904062},
{"learn":[3.969616848],"iteration":478,"passed_time":0.4234746757,"remaining_time":0.4606060669},
{"learn":[3.968533527],"iteration":479,"passed_time":0.4239606057,"remaining_time":0.4592906561},
{"learn":[3.967568753],"iteration":480,"passed_time":0.4244601811,"remaining_time":0.4579934179},
{"learn":[3.966232553],"iteration":481,"passed_time":0.4249707172,"remaining_time":0.4567112686},
{"learn":[3.961522393],"iteration":482,"passed_time":0.4254841786,"remaining_time":0.4554354459},
{"learn":[3.955829553],"iteration":483,"passed_time":0.4260021285,"remaining_time":0.4541675585},
{"learn":[3.954248095],"iteration":484,"passed_time":0.426497937,"remaining_time":0.4528792527},
{"learn":[3.951922606],"iteration":485,"passed_time":0.4270096251,"remaining_time":0.4516110027},
{"learn":[3.94978202],"iteration":486,"passed_time":0.4275764685,"remaining_time":0.4504039596},
{"learn":[3.949518999],"iteration":487,"passed_time":0.428081434,"remaining_time":0.4491346193},
{"learn":[3.945431216],"iteration":488,"passed_time":0.4285956469,"remaining_time":0.4478780687},
{"learn":[3.943249086],"iteration":489,"passed_time":0.4292725445,"remaining_time":0.4467938728},
{"learn":[3.941981548],"iteration":490,"passed_time":0.4297920272,"remaining_time":0.4455481504},
{"learn":[3.936600517],"iteration":491,"passed_time":0.4303096465,"remaining_time":0.4443034561},
{"learn":[3.934476885],"iteration":492,"passed_time":0.4308065069,"remaining_time":0.4430403631},
{"learn":[3.93045798],"iteration":493,"passed_time":0.4313361086,"remaining_time":0.4418139088},
{"learn":[3.925977375],"iteration":494,"passed_time":0.431848448,"remaining_time":0.4405726591},
{"learn":[3.92457993],"iteration":495,"passed_time":0.4323562589,"remaining_time":0.439329747},
{"learn":[3.919849146],"iteration":496,"passed_time":0.4328685081,"remaining_time":0.4380942849},
{"learn":[3.919681964],"iteration":497,"passed_time":0.433358145,"remaining_time":0.4368389333},
{"learn":[3.917633027],"iteration":498,"passed_time":0.4338753234,"remaining_time":0.4356143027},
{"learn":[3.916616419],"iteration":499,"passed_time":0.4343982126,"remaining_time":0.4343982126},
{"learn":[3.912896166],"iteration":500,"passed_time":0.4349125758,"remaining_time":0.4331763978},
{"learn":[3.912769674],"iteration":501,"passed_time":0.4354108288,"remaining_time":0.4319414198},
{"learn":[3.909373788],"iteration":502,"passed_time":0.4359233184,"remaining_time":0.4307234379},
{"learn":[3.906706036],"iteration":503,"passed_time":0.4364435226,"remaining_time":0.4295158476},
{"learn":[3.903895664],"iteration":504,"passed_time":0.4369455426,"remaining_time":0.4282931556},
{"learn":[3.902982967],"iteration":505,"passed_time":0.4374933284,"remaining_time":0.4271179925},
{"learn":[3.900905528],"iteration":506,"passed_time":0.4380462638,"remaining_time":0.4259503117},
{"learn":[3.897463465],"iteration":507,"passed_time":0.438580404,"remaining_time":0.424766848},
{"learn":[3.895918033],"iteration":508,"passed_time":0.4391046958,"remaining_time":0.4235764354},
{"learn":[3.893921936],"iteration":509,"passed_time":0.4396224152,"remaining_time":0.4223823205},
{"learn":[3.890237934],"iteration":510,"passed_time":0.4401295549,"remaining_time":0.4211807286},
{"learn":[3.887311613],"iteration":511,"passed_time":0.4406518028,"remaining_time":0.4199962496},
{"learn":[3.884869735],"iteration":512,"passed_time":0.4412205378,"remaining_time":0.4188584833},
{"learn":[3.882101231],"iteration":513,"passed_time":0.4417899841,"remaining_time":0.4177236037},
{"learn":[3.88060368],"iteration":514,"passed_time":0.4423470172,"remaining_time":0.4165792298},
{"learn":[3.877726076],"iteration":515,"passed_time":0.4429643532,"remaining_time":0.4154936956},
{"learn":[3.874938145],"iteration":516,"passed_time":0.4435504908,"remaining_time":0.414380826},
{"learn":[3.874340833],"iteration":517,"passed_time":0.4441049591,"remaining_time":0.4132405217},
{"learn":[3.873105224],"iteration":518,"passed_time":0.4446339196,"remaining_time":0.4120788349},
{"learn":[3.869800236],"iteration":519,"passed_time":0.4452167309,"remaining_time":0.4109692901},
{"learn":[3.867932518],"iteration":520,"passed_time":0.4457741347,"remaining_time":0.4098384079},
{"learn":[3.866666962],"iteration":521,"passed_time":0.4463136049,"remaining_time":0.408693301},
{"learn":[3.865527652],"iteration":522,"passed_time":0.4468608196,"remaining_time":0.4075575735},
{"learn":[3.861900081],"iteration":523,"passed_time":0.4473901508,"remaining_time":0.4064078469},
{"learn":[3.858502887],"iteration":524,"passed_time":0.4479102347,"remaining_time":0.4052521171},
{"learn":[3.858335097],"iteration":525,"passed_time":0.4484088784,"remaining_time":0.4040794836},
{"learn":[3.855719306],"iteration":526,"passed_time":0.4489311965,"remaining_time":0.4029306564},
{"learn":[3.855137428],"iteration":527,"passed_time":0.4494520318,"remaining_time":0.4017828769},
{"learn":[3.851985706],"iteration":528,"passed_time":0.4499630787,"remaining_time":0.4006287525},
{"learn":[3.851051809],"iteration":529,"passed_time":0.4504586367,"remaining_time":0.3994633193},
{"learn":[3.850679146],"iteration":530,"passed_time":0.4509540544,"remaining_time":0.3983002853},
{"learn":[3.848179484],"iteration":531,"passed_time":0.451457407,"remaining_time":0.3971467415},
{"learn":[3.844551071],"iteration":532,"passed_time":0.4519776311,"remaining_time":0.3960104198},
{"learn":[3.841604794],"iteration":533,"passed_time":0.452495601,"remaining_time":0.3948744384},
{"learn":[3.83969656],"iteration":534,"passed_time":0.4530177588,"remaining_time":0.3937444072},
{"learn":[3.836811463],"iteration":535,"passed_time":0.4535477312,"remaining_time":0.3926234091},
{"learn":[3.834182551],"iteration":536,"passed_time":0.4540500919,"remaining_time":0.3914808055},
{"learn":[3.828012842],"iteration":537,"passed_time":0.4545682222,"remaining_time":0.3903541239},
{"learn":[3.826636176],"iteration":538,"passed_time":0.4550828759,"remaining_time":0.3892267269},
{"learn":[3.826189798],"iteration":539,"passed_time":0.4555850362,"remaining_time":0.3880909568},
{"learn":[3.824104738],"iteration":540,"passed_time":0.4560999504,"remaining_time":0.3869683498},
{"learn":[3.82300218],"iteration":541,"passed_time":0.4565979129,"remaining_time":0.3858336607},
{"learn":[3.817146402],"iteration":542,"passed_time":0.4571150212,"remaining_time":0.3847174304},
{"learn":[3.814638044],"iteration":543,"passed_time":0.4576324902,"remaining_time":0.383603705},
{"learn":[3.812979573],"iteration":544,"passed_time":0.4582332551,"remaining_time":0.3825617084},
{"learn":[3.811938825],"iteration":545,"passed_time":0.4587579577,"remaining_time":0.381458082},
{"learn":[3.811479418],"iteration":546,"passed_time":0.4592617411,"remaining_time":0.3803392481},
{"learn":[3.80742981],"iteration":547,"passed_time":0.459772758,"remaining_time":0.3792286252},
{"learn":[3.805097043],"iteration":548,"passed_time":0.4603072989,"remaining_time":0.3781395115},
{"learn":[3.801577232],"iteration":549,"passed_time":0.4608263008,"remaining_time":0.3770397006},
{"learn":[3.799762083],"iteration":550,"passed_time":0.4613513941,"remaining_time":0.3759469618},
{"learn":[3.796393455],"iteration":551,"passed_time":0.4618732012,"remaining_time":0.3748536125},
{"learn":[3.793486459],"iteration":552,"passed_time":0.46237988,"remaining_time":0.3737501019},
{"learn":[3.792006091],"iteration":553,"passed_time":0.4628938223,"remaining_time":0.3726545934},
{"learn":[3.78932128],"iteration":554,"passed_time":0.4634246564,"remaining_time":0.3715747245},
{"learn":[3.787581812],"iteration":555,"passed_time":0.4639468742,"remaining_time":0.3704899499},
{"learn":[3.785308865],"iteration":556,"passed_time":0.4644620389,"remaining_time":0.3694015857},
{"learn":[3.78465475],"iteration":557,"passed_time":0.4649460052,"remaining_time":0.3682905632},
{"learn":[3.780498869],"iteration":558,"passed_time":0.4654590459,"remaining_time":0.3672047213},
{"learn":[3.778734909],"iteration":559,"passed_time":0.4659612463,"remaining_time":0.3661124078},
{"learn":[3.778652349],"iteration":560,"passed_time":0.4664492902,"remaining_time":0.3650111201},
{"learn":[3.777928006],"iteration":561,"passed_time":0.4669609182,"remaining_time":0.3639303953},
{"learn":[3.776131406],"iteration":562,"passed_time":0.4674845988,"remaining_time":0.3628610474},
{"learn":[3.772925617],"iteration":563,"passed_time":0.4679971687,"remaining_time":0.3617850453},
{"learn":[3.7727745],"iteration":564,"passed_time":0.4684901117,"remaining_time":0.3606959267},
{"learn":[3.771763073],"iteration":565,"passed_time":0.468994907,"remaining_time":0.3596180029},
{"learn":[3.768738162],"iteration":566,"passed_time":0.4695587228,"remaining_time":0.3585871728},
{"learn":[3.767220794],"iteration":567,"passed_time":0.4700755105,"remaining_time":0.3575222192},
{"learn":[3.766691102],"iteration":568,"passed_time":0.4705779012,"remaining_time":0.3564482872},
{"learn":[3.766259335],"iteration":569,"passed_time":0.4710873853,"remaining_time":0.3553817117},
{"learn":[3.76116362],"iteration":570,"passed_time":0.4715975606,"remaining_time":0.3543176068},
{"learn":[3.758633056],"iteration":571,"passed_time":0.4721064636,"remaining_time":0.3532544867},
{"learn":[3.754603809],"iteration":572,"passed_time":0.4726268079,"remaining_time":0.3522018272},
{"learn":[3.754070549],"iteration":573,"passed_time":0.4731232876,"remaining_time":0.351133311},
{"learn":[3.750534319],"iteration":574,"passed_time":0.4736479501,"remaining_time":0.3500876153},
{"learn":[3.746491516],"iteration":575,"passed_time":0.4741576345,"remaining_time":0.3490327032},
{"learn":[3.744210544],"iteration":576,"passed_time":0.4746871561,"remaining_time":0.3479942236},
{"learn":[3.742929991],"iteration":577,"passed_time":0.4752073201,"remaining_time":0.3469506732},
{"learn":[3.740402992],"iteration":578,"passed_time":0.4757253802,"remaining_time":0.3459074008},
{"learn":[3.739644243],"iteration":579,"passed_time":0.4762260878,"remaining_time":0.3448533739},
{"learn":[3.737529404],"iteration":580,"passed_time":0.4767298812,"remaining_time":0.3438034771},
{"learn":[3.737196923],"iteration":581,"passed_time":0.4772306289,"remaining_time":0.3427532695},
{"learn":[3.733954464],"iteration":582,"passed_time":0.4777446214,"remaining_time":0.3417144204},
{"learn":[3.731608623],"iteration":583,"passed_time":0.4782641743,"remaining_time":0.3406813296},
{"learn":[3.729843952],"iteration":584,"passed_time":0.4787969419,"remaining_time":0.339659369},
{"learn":[3.727223798],"iteration":585,"passed_time":0.4793216044,"remaining_time":0.3386333519},
{"learn":[3.725351667],"iteration":586,"passed_time":0.4798404359,"remaining_time":0.3376049404},
{"learn":[3.725026912],"iteration":587,"passed_time":0.4803480364,"remaining_time":0.3365703929},
{"learn":[3.721974565],"iteration":588,"passed_time":0.4808981365,"remaining_time":0.3355672905},
{"learn":[3.720269493],"iteration":589,"passed_time":0.4814808477,"remaining_time":0.3345883857},
{"learn":[3.718907466],"iteration":590,"passed_time":0.4820643904,"remaining_time":0.3336113971},
{"learn":[3.715602912],"iteration":591,"passed_time":0.4826527421,"remaining_time":0.332639052},
{"learn":[3.714463059],"iteration":592,"passed_time":0.483163719,"remaining_time":0.3316148965},
{"learn":[3.710802077],"iteration":593,"passed_time":0.483686578,"remaining_time":0.3306005904},
{"learn":[3.708032435],"iteration":594,"passed_time":0.4842062011,"remaining_time":0.3295857335},
{"learn":[3.703788939],"iteration":595,"passed_time":0.4847143426,"remaining_time":0.3285647557},
{"learn":[3.702500944],"iteration":596,"passed_time":0.4852169337,"remaining_time":0.3275417492},
{"learn":[3.698196925],"iteration":597,"passed_time":0.4857296638,"remaining_time":0.3265272991},
{"learn":[3.69658891],"iteration":598,"passed_time":0.4862462412,"remaining_time":0.3255170997},
{"learn":[3.696124066],"iteration":599,"passed_time":0.4867516275,"remaining_time":0.324501085},
{"learn":[3.693537052],"iteration":600,"passed_time":0.4872811892,"remaining_time":0.3235028194},
{"learn":[3.691343275],"iteration":601,"passed_time":0.4878010526,"remaining_time":0.3224996993},
{"learn":[3.690973831],"iteration":602,"passed_time":0.4883243926,"remaining_time":0.3215004708},
{"learn":[3.686151073],"iteration":603,"passed_time":0.4888343375,"remaining_time":0.3204940359},
{"learn":[3.683921982],"iteration":604,"passed_time":0.4893497427,"remaining_time":0.3194928072},
{"learn":[3.679975271],"iteration":605,"passed_time":0.4898653983,"remaining_time":0.3184933447},
{"learn":[3.674047638],"iteration":606,"passed_time":0.490385432,"remaining_time":0.317498311},
{"learn":[3.673151794],"iteration":607,"passed_time":0.4908936437,"remaining_time":0.3164972177},
{"learn":[3.670953108],"iteration":608,"passed_time":0.4914137476,"remaining_time":0.3155053782},
{"learn":[3.6703947],"iteration":609,"passed_time":0.4919200858,"remaining_time":0.3145062844},
{"learn":[3.668433805],"iteration":610,"passed_time":0.4924428547,"remaining_time":0.3135192643},
{"learn":[3.668304956],"iteration":611,"passed_time":0.4929370802,"remaining_time":0.3125156652},
{"learn":[3.667880012],"iteration":612,"passed_time":0.4934438291,"remaining_time":0.3115216343},
{"learn":[3.667282264],"iteration":613,"passed_time":0.4939427133,"remaining_time":0.3105242465},
{"learn":[3.664611483],"iteration":614,"passed_time":0.494451506,"remaining_time":0.3095346826},
{"learn":[3.662543394],"iteration":615,"passed_time":0.4949660896,"remaining_time":0.3085502896},
{"learn":[3.659041959],"iteration":616,"passed_time":0.4954872956,"remaining_time":0.3075715303},
{"learn":[3.656868545],"iteration":617,"passed_time":0.4960165967,"remaining_time":0.3065992556},
{"learn":[3.654785614],"iteration":618,"passed_time":0.4965382035,"remaining_time":0.3056236761},
{"learn":[3.654566096],"iteration":619,"passed_time":0.497030335,"remaining_time":0.3046314957},
{"learn":[3.651007045],"iteration":620,"passed_time":0.4975552981,"remaining_time":0.3036609629},
{"learn":[3.648921786],"iteration":621,"passed_time":0.498112812,"remaining_time":0.3027116446},
{"learn":[3.647655706],"iteration":622,"passed_time":0.4986152429,"remaining_time":0.3017302513},
{"learn":[3.647241144],"iteration":623,"passed_time":0.4991358377,"remaining_time":0.3007613381},
{"learn":[3.644195689],"iteration":624,"passed_time":0.4996498302,"remaining_time":0.2997898981},
{"learn":[3.642632246],"iteration":625,"passed_time":0.5001659467,"remaining_time":0.2988211886},
{"learn":[3.642523322],"iteration":626,"passed_time":0.5005857027,"remaining_time":0.2977965982},
{"learn":[3.641494659],"iteration":627,"passed_time":0.5010934935,"remaining_time":0.2968260822},
{"learn":[3.63976496],"iteration":628,"passed_time":0.5015991304,"remaining_time":0.2958557669},
{"learn":[3.637945652],"iteration":629,"passed_time":0.502121739,"remaining_time":0.2948968943},
{"learn":[3.636233667],"iteration":630,"passed_time":0.5026245706,"remaining_time":0.2939278392},
{"learn":[3.635304404],"iteration":631,"passed_time":0.5031377315,"remaining_time":0.292966274},
{"learn":[3.632234951],"iteration":632,"passed_time":0.503661903,"remaining_time":0.2920125093},
{"learn":[3.631630987],"iteration":633,"passed_time":0.5041828085,"remaining_time":0.2910582144},
{"learn":[3.630301009],"iteration":634,"passed_time":0.5047030627,"remaining_time":0.29010491},
{"learn":[3.629077964],"iteration":635,"passed_time":0.505207888,"remaining_time":0.2891441372},
{"learn":[3.628004522],"iteration":636,"passed_time":0.5057212393,"remaining_time":0.2881896544},
{"learn":[3.625062876],"iteration":637,"passed_time":0.5062347408,"remaining_time":0.2872366398},
{"learn":[3.624917986],"iteration":638,"passed_time":0.5067317014,"remaining_time":0.286275656},
{"learn":[3.622887087],"iteration":639,"passed_time":0.5072436601,"remaining_time":0.2853245588},
{"learn":[3.621220865],"iteration":640,"passed_time":0.5077662687,"remaining_time":0.2843807964},
{"learn":[3.621143844],"iteration":641,"passed_time":0.5082488424,"remaining_time":0.2834160211},
{"learn":[3.620822821],"iteration":642,"passed_time":0.5087313659,"remaining_time":0.2824527179},
{"learn":[3.619202826],"iteration":643,"passed_time":0.509249416,"remaining_time":0.2815105467},
{"learn":[3.618204882],"iteration":644,"passed_time":0.5097555738,"remaining_time":0.2805631453},
{"learn":[3.614259666],"iteration":645,"passed_time":0.5102840033,"remaining_time":0.2796293145},
{"learn":[3.613415661],"iteration":646,"passed_time":0.5108172719,"remaining_time":0.2786993771},
{"learn":[3.611096773],"iteration":647,"passed_time":0.5113333683,"remaining_time":0.2777613359},
{"learn":[3.610820695],"iteration":648,"passed_time":0.5119402347,"remaining_time":0.2768736863},
{"learn":[3.609290065],"iteration":649,"passed_time":0.5125589132,"remaining_time":0.275993261},
{"learn":[3.60897947],"iteration":650,"passed_time":0.5131086226,"remaining_time":0.2750766656},
{"learn":[3.606570702],"iteration":651,"passed_time":0.5136399576,"remaining_time":0.2741513884},
{"learn":[3.606292637],"iteration":652,"passed_time":0.5141469169,"remaining_time":0.2732143647},
{"learn":[3.602753838],"iteration":653,"passed_time":0.5146663896,"remaining_time":0.2722852765},
{"learn":[3.599755869],"iteration":654,"passed_time":0.5151893589,"remaining_time":0.2713592806},
{"learn":[3.599509575],"iteration":655,"passed_time":0.5156922306,"remaining_time":0.2704239746},
{"learn":[3.595337722],"iteration":656,"passed_time":0.5162202193,"remaining_time":0.2695030977},
{"learn":[3.595168561],"iteration":657,"passed_time":0.5167110083,"remaining_time":0.2685640803},
{"learn":[3.59290559],"iteration":658,"passed_time":0.5172232274,"remaining_time":0.2676375122},
{"learn":[3.592015928],"iteration":659,"passed_time":0.5177392537,"remaining_time":0.266714161},
{"learn":[3.590680403],"iteration":660,"passed_time":0.5182406927,"remaining_time":0.265784561},
{"learn":[3.590361532],"iteration":661,"passed_time":0.5187461091,"remaining_time":0.2648582853},
{"learn":[3.589069739],"iteration":662,"passed_time":0.5192604022,"remaining_time":0.2639377912},
{"learn":[3.585010186],"iteration":663,"passed_time":0.5197748756,"remaining_time":0.2630186117},
{"learn":[3.582997552],"iteration":664,"passed_time":0.5203540701,"remaining_time":0.2621332534},
{"learn":[3.582119256],"iteration":665,"passed_time":0.5209131571,"remaining_time":0.2612387304},
{"learn":[3.579019356],"iteration":666,"passed_time":0.5214412259,"remaining_time":0.2603297275},
{"learn":[3.57719559],"iteration":667,"passed_time":0.521966229,"remaining_time":0.2594203414},
{"learn":[3.574050046],"iteration":668,"passed_time":0.5224896792,"remaining_time":0.258511336},
{"learn":[3.572204518],"iteration":669,"passed_time":0.5230222364,"remaining_time":0.2576079672},
{"learn":[3.569508025],"iteration":670,"passed_time":0.5235471193,"remaining_time":0.2567019408},
{"learn":[3.566268704],"iteration":671,"passed_time":0.5240884831,"remaining_time":0.2558050929},
{"learn":[3.562564052],"iteration":672,"passed_time":0.5246563063,"remaining_time":0.2549221578},
{"learn":[3.561173586],"iteration":673,"passed_time":0.5251841347,"remaining_time":0.2540208129},
{"learn":[3.559551904],"iteration":674,"passed_time":0.5257105605,"remaining_time":0.2531198995},
{"learn":[3.558593054],"iteration":675,"passed_time":0.5263594355,"remaining_time":0.2522787827},
{"learn":[3.555647008],"iteration":676,"passed_time":0.5270262742,"remaining_time":0.2514468044},
{"learn":[3.553100059],"iteration":677,"passed_time":0.5276915901,"remaining_time":0.25061459},
{"learn":[3.55085578],"iteration":678,"passed_time":0.5283400544,"remaining_time":0.2497749005},
{"learn":[3.550737965],"iteration":679,"passed_time":0.5289443059,"remaining_time":0.2489149675},
{"learn":[3.549408772],"iteration":680,"passed_time":0.5295794853,"remaining_time":0.2480702728},
{"learn":[3.547390589],"iteration":681,"passed_time":0.5302163178,"remaining_time":0.2472269634},
{"learn":[3.54723575],"iteration":682,"passed_time":0.5308256789,"remaining_time":0.2463715083},
{"learn":[3.543988891],"iteration":683,"passed_time":0.5314784412,"remaining_time":0.2455368237},
{"learn":[3.543868508],"iteration":684,"passed_time":0.5320990233,"remaining_time":0.244687872},
{"learn":[3.542752124],"iteration":685,"passed_time":0.5327340424,"remaining_time":0.2438461943},
{"learn":[3.541334315],"iteration":686,"passed_time":0.5333659857,"remaining_time":0.2430037169},
{"learn":[3.540208266],"iteration":687,"passed_time":0.5340003336,"remaining_time":0.242162942},
{"learn":[3.537730983],"iteration":688,"passed_time":0.5346486476,"remaining_time":0.2413290703},
{"learn":[3.53419867],"iteration":689,"passed_time":0.5352978433,"remaining_time":0.2404961325},
{"learn":[3.532628335],"iteration":690,"passed_time":0.5359334234,"remaining_time":0.239657638},
{"learn":[3.532204987],"iteration":691,"passed_time":0.5365798539,"remaining_time":0.2388245593},
{"learn":[3.530618147],"iteration":692,"passed_time":0.5372132099,"remaining_time":0.2379862272},
{"learn":[3.528909306],"iteration":693,"passed_time":0.5378575364,"remaining_time":0.237153323},
{"learn":[3.526700678],"iteration":694,"passed_time":0.5385139757,"remaining_time":0.2363262771},
{"learn":[3.526439574],"iteration":695,"passed_time":0.5391420418,"remaining_time":0.2354873286},
{"learn":[3.525784216],"iteration":696,"passed_time":0.5397773714,"remaining_time":0.2346521428},
{"learn":[3.524112693],"iteration":697,"passed_time":0.5404006987,"remaining_time":0.2338123367},
{"learn":[3.522813541],"iteration":698,"passed_time":0.5409257418,"remaining_time":0.2329308273},
{"learn":[3.519148203],"iteration":699,"passed_time":0.5414444832,"remaining_time":0.2320476357},
{"learn":[3.517236747],"iteration":700,"passed_time":0.5419570731,"remaining_time":0.23116286},
{"learn":[3.515603888],"iteration":701,"passed_time":0.5424842502,"remaining_time":0.230285337},
{"learn":[3.51263524],"iteration":702,"passed_time":0.5430160962,"remaining_time":0.2294107832},
{"learn":[3.51123442],"iteration":703,"passed_time":0.5435318219,"remaining_time":0.2285304251},
{"learn":[3.50828027],"iteration":704,"passed_time":0.5440508939,"remaining_time":0.2276525017},
{"learn":[3.508265537],"iteration":705,"passed_time":0.5443771147,"remaining_time":0.2266952857},
{"learn":[3.506774876],"iteration":706,"passed_time":0.5448962769,"remaining_time":0.2258198149},
{"learn":[3.50552068],"iteration":707,"passed_time":0.5453969244,"remaining_time":0.2249377146},
{"learn":[3.501973993],"iteration":708,"passed_time":0.5459036032,"remaining_time":0.2240591658},
{"learn":[3.498880354],"iteration":709,"passed_time":0.546422585,"remaining_time":0.2231866897},
{"learn":[3.497370959],"iteration":710,"passed_time":0.5469329607,"remaining_time":0.2223117098},
{"learn":[3.496050455],"iteration":711,"passed_time":0.5474474441,"remaining_time":0.2214394156},
{"learn":[3.495630067],"iteration":712,"passed_time":0.5479471899,"remaining_time":0.2205621929},
{"learn":[3.49550669],"iteration":713,"passed_time":0.5484478775,"remaining_time":0.2196864047},
{"learn":[3.493652375],"iteration":714,"passed_time":0.5489641643,"remaining_time":0.2188178837},
{"learn":[3.491915684],"iteration":715,"passed_time":0.5494737986,"remaining_time":0.2179477078},
{"learn":[3.490303956],"iteration":716,"passed_time":0.549979716,"remaining_time":0.2170770706},
{"learn":[3.488363853],"iteration":717,"passed_time":0.5505013828,"remaining_time":0.216213635},
{"learn":[3.485483936],"iteration":718,"passed_time":0.5510280891,"remaining_time":0.2153531197},
{"learn":[3.483763466],"iteration":719,"passed_time":0.5515443358,"remaining_time":0.2144894639},
{"learn":[3.481642352],"iteration":720,"passed_time":0.5520611736,"remaining_time":0.2136270006},
{"learn":[3.479826119],"iteration":721,"passed_time":0.5525863771,"remaining_time":0.2127687158},
{"learn":[3.478588728],"iteration":722,"passed_time":0.5530955105,"remaining_time":0.2119051956},
{"learn":[3.475390887],"iteration":723,"passed_time":0.5536309231,"remaining_time":0.2110526723},
{"learn":[3.472636852],"iteration":724,"passed_time":0.5541411785,"remaining_time":0.2101914815},
{"learn":[3.47061883],"iteration":725,"passed_time":0.5546778635,"remaining_time":0.2093412322},
{"learn":[3.46953149],"iteration":726,"passed_time":0.5551908541,"remaining_time":0.208482948},
{"learn":[3.467217162],"iteration":727,"passed_time":0.5557334702,"remaining_time":0.2076366812},
{"learn":[3.465686216],"iteration":728,"passed_time":0.5562548365,"remaining_time":0.206783348},
{"learn":[3.462631216],"iteration":729,"passed_time":0.55676937,"remaining_time":0.2059283971},
{"learn":[3.461451053],"iteration":730,"passed_time":0.5572751771,"remaining_time":0.2050711664},
{"learn":[3.458950469],"iteration":731,"passed_time":0.5577961226,"remaining_time":0.2042204383},
{"learn":[3.458072145],"iteration":732,"passed_time":0.5583030419,"remaining_time":0.2033655009},
{"learn":[3.454364268],"iteration":733,"passed_time":0.5588262015,"remaining_time":0.2025173973},
{"learn":[3.453243406],"iteration":734,"passed_time":0.559347147,"remaining_time":0.2016693795},
{"learn":[3.453017963],"iteration":735,"passed_time":0.5598532347,"remaining_time":0.2008169211},
{"learn":[3.45201581],"iteration":736,"passed_time":0.5603654539,"remaining_time":0.1999675907},
{"learn":[3.449510107],"iteration":737,"passed_time":0.560888864,"remaining_time":0.1991231468},
{"learn":[3.447189189],"iteration":738,"passed_time":0.5614083768,"remaining_time":0.1982781953},
{"learn":[3.446423605],"iteration":739,"passed_time":0.5619153361,"remaining_time":0.1974297127},
{"learn":[3.445531987],"iteration":740,"passed_time":0.5624300399,"remaining_time":0.1965848588},
{"learn":[3.445328199],"iteration":741,"passed_time":0.5629228628,"remaining_time":0.1957332865},
{"learn":[3.443327544],"iteration":742,"passed_time":0.5634481264,"remaining_time":0.194893901},
{"learn":[3.441475798],"iteration":743,"passed_time":0.5639731896,"remaining_time":0.194055291},
{"learn":[3.439046501],"iteration":744,"passed_time":0.5645053461,"remaining_time":0.1932199507},
{"learn":[3.435899469],"iteration":745,"passed_time":0.5650384544,"remaining_time":0.1923857472},
{"learn":[3.433988352],"iteration":746,"passed_time":0.5655554825,"remaining_time":0.1915469037},
{"learn":[3.433413263],"iteration":747,"passed_time":0.5660782915,"remaining_time":0.1907108683},
{"learn":[3.429944699],"iteration":748,"passed_time":0.5665947386,"remaining_time":0.1898735372},
{"learn":[3.429291634],"iteration":749,"passed_time":0.5671126584,"remaining_time":0.1890375528},
{"learn":[3.429175603],"iteration":750,"passed_time":0.5676291857,"remaining_time":0.1882019537},
{"learn":[3.428780323],"iteration":751,"passed_time":0.568136155,"remaining_time":0.1873640511},
{"learn":[3.423893341],"iteration":752,"passed_time":0.5687709737,"remaining_time":0.1865689648},
{"learn":[3.421024316],"iteration":753,"passed_time":0.5693920167,"remaining_time":0.1857698091},
{"learn":[3.420969872],"iteration":754,"passed_time":0.570005776,"remaining_time":0.1849687617},
{"learn":[3.419544785],"iteration":755,"passed_time":0.5706455941,"remaining_time":0.1841766203},
{"learn":[3.417057977],"iteration":756,"passed_time":0.571327541,"remaining_time":0.1833984049},
{"learn":[3.415160245],"iteration":757,"passed_time":0.571979562,"remaining_time":0.1826108892},
{"learn":[3.412854597],"iteration":758,"passed_time":0.5726233876,"remaining_time":0.1818211283},
{"learn":[3.410926347],"iteration":759,"passed_time":0.5732808688,"remaining_time":0.1810360638},
{"learn":[3.408963843],"iteration":760,"passed_time":0.5739297338,"remaining_time":0.1802486286},
{"learn":[3.407629634],"iteration":761,"passed_time":0.5745625087,"remaining_time":0.1794565316},
{"learn":[3.404384724],"iteration":762,"passed_time":0.5752060538,"remaining_time":0.1786681976},
{"learn":[3.403041656],"iteration":763,"passed_time":0.5758437479,"remaining_time":0.1778784352},
{"learn":[3.401101731],"iteration":764,"passed_time":0.5765018002,"remaining_time":0.1770953242},
{"learn":[3.400890668],"iteration":765,"passed_time":0.577130808,"remaining_time":0.1763036672},
{"learn":[3.399289941],"iteration":766,"passed_time":0.577771658,"remaining_time":0.1755160317},
{"learn":[3.399202366],"iteration":767,"passed_time":0.5783970692,"remaining_time":0.1747241146},
{"learn":[3.397447845],"iteration":768,"passed_time":0.5790315974,"remaining_time":0.1739353693},
{"learn":[3.394655341],"iteration":769,"passed_time":0.5796815244,"remaining_time":0.1731516242},
{"learn":[3.393228229],"iteration":770,"passed_time":0.5803220939,"remaining_time":0.1723654468},
{"learn":[3.389691197],"iteration":771,"passed_time":0.5809749965,"remaining_time":0.1715832891},
{"learn":[3.389626772],"iteration":772,"passed_time":0.5815540608,"remaining_time":0.1707797824},
{"learn":[3.388480222],"iteration":773,"passed_time":0.5821388759,"remaining_time":0.1699785348},
{"learn":[3.388215066],"iteration":774,"passed_time":0.5826666542,"remaining_time":0.1691612867},
{"learn":[3.386324358],"iteration":775,"passed_time":0.5831868884,"remaining_time":0.168342607},
{"learn":[3.383913061],"iteration":776,"passed_time":0.5836995183,"remaining_time":0.167522513},
{"learn":[3.382839768],"iteration":777,"passed_time":0.5842165665,"remaining_time":0.1667044701},
{"learn":[3.381961844],"iteration":778,"passed_time":0.5847509973,"remaining_time":0.1658921314},
{"learn":[3.381521703],"iteration":779,"passed_time":0.5852554419,"remaining_time":0.1650720477},
{"learn":[3.380918963],"iteration":780,"passed_time":0.585765497,"remaining_time":0.1642543455},
{"learn":[3.377139006],"iteration":781,"passed_time":0.5862962809,"remaining_time":0.1634432087},
{"learn":[3.376004372],"iteration":782,"passed_time":0.5868179478,"remaining_time":0.1626302614},
{"learn":[3.373826468],"iteration":783,"passed_time":0.5873209597,"remaining_time":0.1618129175},
{"learn":[3.373546786],"iteration":784,"passed_time":0.587840222,"remaining_time":0.1610008251},
{"learn":[3.372109181],"iteration":785,"passed_time":0.5883594744,"remaining_time":0.1601894752},
{"learn":[3.370764924],"iteration":786,"passed_time":0.588867686,"remaining_time":0.1593758794},
{"learn":[3.367833107],"iteration":787,"passed_time":0.5893825001,"remaining_time":0.158564835},
{"learn":[3.36450404],"iteration":788,"passed_time":0.5898901707,"remaining_time":0.1577526312},
{"learn":[3.361794558],"iteration":789,"passed_time":0.5904085314,"remaining_time":0.15694404},
{"learn":[3.356880529],"iteration":790,"passed_time":0.590938614,"remaining_time":0.1561392798},
{"learn":[3.353843509],"iteration":791,"passed_time":0.5914699589,"remaining_time":0.1553355448},
{"learn":[3.353640253],"iteration":792,"passed_time":0.5919662683,"remaining_time":0.1545233512},
{"learn":[3.353055088],"iteration":793,"passed_time":0.5924632089,"remaining_time":0.1537121172},
{"learn":[3.351415617],"iteration":794,"passed_time":0.5929760091,"remaining_time":0.1529057634},
{"learn":[3.349169061],"iteration":795,"passed_time":0.5934927067,"remaining_time":0.1521011459},
{"learn":[3.346211014],"iteration":796,"passed_time":0.5940422056,"remaining_time":0.1513056057},
{"learn":[3.344560452],"iteration":797,"passed_time":0.5945579113,"remaining_time":0.1505021279},
{"learn":[3.344445461],"iteration":798,"passed_time":0.595123811,"remaining_time":0.1497119975},
{"learn":[3.342608898],"iteration":799,"passed_time":0.5958141002,"remaining_time":0.148953525},
{"learn":[3.339572899],"iteration":800,"passed_time":0.596346407,"remaining_time":0.1481559738},
{"learn":[3.339309302],"iteration":801,"passed_time":0.5968320564,"remaining_time":0.147347565},
{"learn":[3.33698088],"iteration":802,"passed_time":0.5973605059,"remaining_time":0.1465504604},
{"learn":[3.334746342],"iteration":803,"passed_time":0.5978802592,"remaining_time":0.145751904},
{"learn":[3.332048511],"iteration":804,"passed_time":0.5984017657,"remaining_time":0.144954465},
{"learn":[3.331932544],"iteration":805,"passed_time":0.5989195153,"remaining_time":0.1441568064},
{"learn":[3.330541133],"iteration":806,"passed_time":0.5994145522,"remaining_time":0.1433544096},
{"learn":[3.329124989],"iteration":807,"passed_time":0.5999295366,"remaining_time":0.1425575136},
{"learn":[3.32583918],"iteration":808,"passed_time":0.6004362354,"remaining_time":0.1417593584},
{"learn":[3.325287299],"iteration":809,"passed_time":0.6009265035,"remaining_time":0.1409580687},
{"learn":[3.322745162],"iteration":810,"passed_time":0.6014318397,"remaining_time":0.1401610576},
{"learn":[3.319733662],"iteration":811,"passed_time":0.6019335091,"remaining_time":0.1393639159},
{"learn":[3.318080007],"iteration":812,"passed_time":0.6024468504,"remaining_time":0.1385701858},
{"learn":[3.317179538],"iteration":813,"passed_time":0.6029525874,"remaining_time":0.137775407},
{"learn":[3.315685949],"iteration":814,"passed_time":0.6034743044,"remaining_time":0.1369849648},
{"learn":[3.314944576],"iteration":815,"passed_time":0.6039936569,"remaining_time":0.1361946481},
{"learn":[3.312369052],"iteration":816,"passed_time":0.6045110558,"remaining_time":0.1354045572},
{"learn":[3.312321621],"iteration":817,"passed_time":0.6048950248,"remaining_time":0.1345854456},
{"learn":[3.309465776],"iteration":818,"passed_time":0.605409448,"remaining_time":0.1337962272},
{"learn":[3.308307377],"iteration":819,"passed_time":0.6059183209,"remaining_time":0.1330064607},
{"learn":[3.308076804],"iteration":820,"passed_time":0.6064009046,"remaining_time":0.1322116467},
{"learn":[3.305643326],"iteration":821,"passed_time":0.6069169209,"remaining_time":0.131424832},
{"learn":[3.304154814],"iteration":822,"passed_time":0.6074140718,"remaining_time":0.1306346181},
{"learn":[3.303076321],"iteration":823,"passed_time":0.6079515683,"remaining_time":0.129853733},
{"learn":[3.301746372],"iteration":824,"passed_time":0.6084642283,"remaining_time":0.1290681696},
{"learn":[3.301345455],"iteration":825,"passed_time":0.6089700856,"remaining_time":0.128281834},
{"learn":[3.299181039],"iteration":826,"passed_time":0.609535154,"remaining_time":0.127508563},
{"learn":[3.297989357],"iteration":827,"passed_time":0.6101881468,"remaining_time":0.1267540595},
{"learn":[3.294775182],"iteration":828,"passed_time":0.6108529516,"remaining_time":0.1260022373},
{"learn":[3.293840636],"iteration":829,"passed_time":0.6114931505,"remaining_time":0.125245585},
{"learn":[3.289279397],"iteration":830,"passed_time":0.6121443899,"remaining_time":0.1244914584},
{"learn":[3.286204979],"iteration":831,"passed_time":0.6127902994,"remaining_time":0.1237365028},
{"learn":[3.284833593],"iteration":832,"passed_time":0.6134213511,"remaining_time":0.1229788303},
{"learn":[3.283519914],"iteration":833,"passed_time":0.6140559194,"remaining_time":0.1222221614},
{"learn":[3.282853026],"iteration":834,"passed_time":0.6146685366,"remaining_time":0.1214614473},
{"learn":[3.281944673],"iteration":835,"passed_time":0.6151755059,"remaining_time":0.1206803624},
{"learn":[3.279764865],"iteration":836,"passed_time":0.6156943975,"remaining_time":0.1199022542},
{"learn":[3.277468839],"iteration":837,"passed_time":0.616205695,"remaining_time":0.1191232966},
{"learn":[3.277124974],"iteration":838,"passed_time":0.6167132053,"remaining_time":0.1183442504},
{"learn":[3.275636037],"iteration":839,"passed_time":0.6172151452,"remaining_time":0.1175647896},
{"learn":[3.274413635],"iteration":840,"passed_time":0.6177141597,"remaining_time":0.1167854357},
{"learn":[3.272636087],"iteration":841,"passed_time":0.6182151578,"remaining_time":0.1160071199},
{"learn":[3.269644466],"iteration":842,"passed_time":0.6187261447,"remaining_time":0.1152313223},
{"learn":[3.26852083],"iteration":843,"passed_time":0.6192383438,"remaining_time":0.1144563763},
{"learn":[3.267820927],"iteration":844,"passed_time":0.619751094,"remaining_time":0.1136821533},
{"learn":[3.267331099],"iteration":845,"passed_time":0.6202519619,"remaining_time":0.1129063855},
{"learn":[3.267231014],"iteration":846,"passed_time":0.6207414384,"remaining_time":0.1121292091},
{"learn":[3.267158695],"iteration":847,"passed_time":0.6212340509,"remaining_time":0.1113532733},
{"learn":[3.264718705],"iteration":848,"passed_time":0.6217456689,"remaining_time":0.1105813852},
{"learn":[3.261678512],"iteration":849,"passed_time":0.622263158,"remaining_time":0.1098111455},
{"learn":[3.261368381],"iteration":850,"passed_time":0.6227586959,"remaining_time":0.1090376565},
{"learn":[3.260128799],"iteration":851,"passed_time":0.6232676589,"remaining_time":0.108267152},
{"learn":[3.258972952],"iteration":852,"passed_time":0.6239220844,"remaining_time":0.1075223287},
{"learn":[3.258724846],"iteration":853,"passed_time":0.6244397838,"remaining_time":0.1067543424},
{"learn":[3.25686724],"iteration":854,"passed_time":0.6249679729,"remaining_time":0.1059887205},
{"learn":[3.255750259],"iteration":855,"passed_time":0.6254802522,"remaining_time":0.105220977},
{"learn":[3.254915866],"iteration":856,"passed_time":0.6259831138,"remaining_time":0.1044522582},
{"learn":[3.254348625],"iteration":857,"passed_time":0.6264835108,"remaining_time":0.1036837512},
{"learn":[3.253408514],"iteration":858,"passed_time":0.6269936361,"remaining_time":0.1029174653},
{"learn":[3.253291714],"iteration":859,"passed_time":0.627475288,"remaining_time":0.1021471399},
{"learn":[3.250186342],"iteration":860,"passed_time":0.6280031164,"remaining_time":0.1013849398},
{"learn":[3.249141318],"iteration":861,"passed_time":0.6285085328,"remaining_time":0.1006196955},
{"learn":[3.246300388],"iteration":862,"passed_time":0.6290236975,"remaining_time":0.09985660087},
{"learn":[3.245205135],"iteration":863,"passed_time":0.6295376599,"remaining_time":0.09909389091},
{"learn":[3.244403535],"iteration":864,"passed_time":0.6300469436,"remaining_time":0.09833102587},
{"learn":[3.244211781],"iteration":865,"passed_time":0.6305417702,"remaining_time":0.09756650947},
{"learn":[3.242286347],"iteration":866,"passed_time":0.6310582072,"remaining_time":0.09680593029},
{"learn":[3.239606746],"iteration":867,"passed_time":0.6315533845,"remaining_time":0.09604268059},
{"learn":[3.236773361],"iteration":868,"passed_time":0.6320921734,"remaining_time":0.09528662222},
{"learn":[3.234552446],"iteration":869,"passed_time":0.6326210638,"remaining_time":0.09452958424},
{"learn":[3.233724647],"iteration":870,"passed_time":0.6331553142,"remaining_time":0.09377386398},
{"learn":[3.230851485],"iteration":871,"passed_time":0.6336712904,"remaining_time":0.09301596923},
{"learn":[3.227728941],"iteration":872,"passed_time":0.6341844613,"remaining_time":0.0922582206},
{"learn":[3.225787575],"iteration":873,"passed_time":0.6347024713,"remaining_time":0.09150172927},
{"learn":[3.222797487],"iteration":874,"passed_time":0.6352264725,"remaining_time":0.09074663893},
{"learn":[3.22137014],"iteration":875,"passed_time":0.6357411062,"remaining_time":0.0899907502},
{"learn":[3.219701963],"iteration":876,"passed_time":0.6362411025,"remaining_time":0.08923335873},
{"learn":[3.21783327],"iteration":877,"passed_time":0.6367713554,"remaining_time":0.08848075782},
{"learn":[3.217713355],"iteration":878,"passed_time":0.6374206995,"remaining_time":0.08774505647},
{"learn":[3.217666091],"iteration":879,"passed_time":0.6379034735,"remaining_time":0.0869868373},
{"learn":[3.214962005],"iteration":880,"passed_time":0.6384188285,"remaining_time":0.08623364426},
{"learn":[3.214081828],"iteration":881,"passed_time":0.6389290239,"remaining_time":0.08548030025},
{"learn":[3.213358337],"iteration":882,"passed_time":0.6394400609,"remaining_time":0.08472761848},
{"learn":[3.210850401],"iteration":883,"passed_time":0.6399510377,"remaining_time":0.08397547554},
{"learn":[3.207810328],"iteration":884,"passed_time":0.6404915298,"remaining_time":0.08322771291},
{"learn":[3.204935073],"iteration":885,"passed_time":0.6410442749,"remaining_time":0.08248199473},
{"learn":[3.20280198],"iteration":886,"passed_time":0.6415816511,"remaining_time":0.08173475375},
{"learn":[3.200663495],"iteration":887,"passed_time":0.6420973067,"remaining_time":0.08098524589},
{"learn":[3.197301669],"iteration":888,"passed_time":0.6426218089,"remaining_time":0.08023736871},
{"learn":[3.195666943],"iteration":889,"passed_time":0.6431376649,"remaining_time":0.07948892487},
{"learn":[3.193886506],"iteration":890,"passed_time":0.6436531902,"remaining_time":0.07874096266},
{"learn":[3.190601248],"iteration":891,"passed_time":0.6441704588,"remaining_time":0.07799373268},
{"learn":[3.188983797],"iteration":892,"passed_time":0.6446801332,"remaining_time":0.07724610779},
{"learn":[3.187365749],"iteration":893,"passed_time":0.6451950374,"remaining_time":0.07649963531},
{"learn":[3.186160771],"iteration":894,"passed_time":0.6457073768,"remaining_time":0.0757533794},
{"learn":[3.185358981],"iteration":895,"passed_time":0.6462148871,"remaining_time":0.07500708511},
{"learn":[3.183832164],"iteration":896,"passed_time":0.6467212754,"remaining_time":0.07426119439},
{"learn":[3.183106966],"iteration":897,"passed_time":0.6472304589,"remaining_time":0.07351615457},
{"learn":[3.182838152],"iteration":898,"passed_time":0.6477245641,"remaining_time":0.07276994547},
{"learn":[3.180835453],"iteration":899,"passed_time":0.6482559391,"remaining_time":0.07202843768},
{"learn":[3.179957348],"iteration":900,"passed_time":0.6487629185,"remaining_time":0.07128471579},
{"learn":[3.179752966],"iteration":901,"passed_time":0.649268375,"remaining_time":0.07054135338},
{"learn":[3.178851983],"iteration":902,"passed_time":0.6497961833,"remaining_time":0.06980091892},
{"learn":[3.176748586],"iteration":903,"passed_time":0.6503000969,"remaining_time":0.06905841737},
{"learn":[3.172960988],"iteration":904,"passed_time":0.6508307807,"remaining_time":0.06831925322},
{"learn":[3.172794225],"iteration":905,"passed_time":0.6513159191,"remaining_time":0.06757582384},
{"learn":[3.169996507],"iteration":906,"passed_time":0.6518619516,"remaining_time":0.06683920783},
{"learn":[3.16813015],"iteration":907,"passed_time":0.6523852515,"remaining_time":0.0661007083},
{"learn":[3.166920871],"iteration":908,"passed_time":0.6528914194,"remaining_time":0.06536096717},
{"learn":[3.16531606],"iteration":909,"passed_time":0.6534009334,"remaining_time":0.06462207034},
{"learn":[3.162035247],"iteration":910,"passed_time":0.6539082835,"remaining_time":0.06388346568},
{"learn":[3.16189467],"iteration":911,"passed_time":0.6544056348,"remaining_time":0.06314440336},
{"learn":[3.161008416],"iteration":912,"passed_time":0.6549183749,"remaining_time":0.06240733693},
{"learn":[3.160560787],"iteration":913,"passed_time":0.6554072404,"remaining_time":0.06166851496},
{"learn":[3.160416261],"iteration":914,"passed_time":0.655900995,"remaining_time":0.06093069352},
{"learn":[3.15844291],"iteration":915,"passed_time":0.6564219405,"remaining_time":0.06019589847},
{"learn":[3.155040501],"iteration":916,"passed_time":0.6569219868,"remaining_time":0.0594596782},
{"learn":[3.154937548],"iteration":917,"passed_time":0.6574151603,"remaining_time":0.05872335855},
{"learn":[3.153721161],"iteration":918,"passed_time":0.6579117502,"remaining_time":0.05798786917},
{"learn":[3.153170511],"iteration":919,"passed_time":0.6584314133,"remaining_time":0.05725490551},
{"learn":[3.153113601],"iteration":920,"passed_time":0.6592601552,"remaining_time":0.05654891668},
{"learn":[3.150607379],"iteration":921,"passed_time":0.6597863806,"remaining_time":0.05581706907},
{"learn":[3.148408359],"iteration":922,"passed_time":0.6603127462,"remaining_time":0.05508567872},
{"learn":[3.147495728],"iteration":923,"passed_time":0.6608604418,"remaining_time":0.05435648656},
{"learn":[3.146946235],"iteration":924,"passed_time":0.6613858657,"remaining_time":0.053625881},
{"learn":[3.14472738],"iteration":925,"passed_time":0.6619089051,"remaining_time":0.05289552806},
{"learn":[3.144469477],"iteration":926,"passed_time":0.662408681,"remaining_time":0.05216379041},
{"learn":[3.142975516],"iteration":927,"passed_time":0.6629214712,"remaining_time":0.05143356242},
{"learn":[3.14079113],"iteration":928,"passed_time":0.6634290317,"remaining_time":0.05070340285},
{"learn":[3.138173032],"iteration":929,"passed_time":0.6639528225,"remaining_time":0.04997494363},
{"learn":[3.136352813],"iteration":930,"passed_time":0.6644574675,"remaining_time":0.04924550511},
{"learn":[3.133735004],"iteration":931,"passed_time":0.6649842859,"remaining_time":0.04851816678},
{"learn":[3.1319496],"iteration":932,"passed_time":0.6655267817,"remaining_time":0.04779238411},
{"learn":[3.129865343],"iteration":933,"passed_time":0.6660502419,"remaining_time":0.04706564879},
{"learn":[3.129830206],"iteration":934,"passed_time":0.6664394107,"remaining_time":0.04633001251},
{"learn":[3.126676562],"iteration":935,"passed_time":0.6669673092,"remaining_time":0.04560460234},
{"learn":[3.12645665],"iteration":936,"passed_time":0.6674743987,"remaining_time":0.04487821464},
{"learn":[3.126378007],"iteration":937,"passed_time":0.6679580744,"remaining_time":0.04415074693},
{"learn":[3.124621914],"iteration":938,"passed_time":0.6684638716,"remaining_time":0.04342523553},
{"learn":[3.123379018],"iteration":939,"passed_time":0.6689664427,"remaining_time":0.0426999857},
{"learn":[3.123332451],"iteration":940,"passed_time":0.6694559193,"remaining_time":0.04197438814},
{"learn":[3.122432444],"iteration":941,"passed_time":0.669969511,"remaining_time":0.04125077668},
{"learn":[3.121889006],"iteration":942,"passed_time":0.6704687158,"remaining_time":0.04052674104},
{"learn":[3.121070914],"iteration":943,"passed_time":0.6709747333,"remaining_time":0.03980358588},
{"learn":[3.118444705],"iteration":944,"passed_time":0.6714818529,"remaining_time":0.0390809544},
{"learn":[3.116820458],"iteration":945,"passed_time":0.6719970377,"remaining_time":0.03835923894},
{"learn":[3.114971041],"iteration":946,"passed_time":0.6725076839,"remaining_time":0.03763770564},
{"learn":[3.114685138],"iteration":947,"passed_time":0.6730154146,"remaining_time":0.03691645734},
{"learn":[3.113399363],"iteration":948,"passed_time":0.6735199795,"remaining_time":0.03619548889},
{"learn":[3.110575399],"iteration":949,"passed_time":0.6740262875,"remaining_time":0.03547506777},
{"learn":[3.110466553],"iteration":950,"passed_time":0.6745147723,"remaining_time":0.03475417859},
{"learn":[3.108691641],"iteration":951,"passed_time":0.6750255187,"remaining_time":0.0340349001},
{"learn":[3.107898017],"iteration":952,"passed_time":0.6757970434,"remaining_time":0.03332892029},
{"learn":[3.105551729],"iteration":953,"passed_time":0.6763233089,"remaining_time":0.03261097716},
{"learn":[3.104824945],"iteration":954,"passed_time":0.6768347766,"remaining_time":0.03189273816},
{"learn":[3.103186704],"iteration":955,"passed_time":0.6773527766,"remaining_time":0.0311752324},
{"learn":[3.102330655],"iteration":956,"passed_time":0.6778663984,"remaining_time":0.03045794684},
{"learn":[3.102291298],"iteration":957,"passed_time":0.678345215,"remaining_time":0.02973956057},
{"learn":[3.100363529],"iteration":958,"passed_time":0.6788709595,"remaining_time":0.02902368023},
{"learn":[3.097871596],"iteration":959,"passed_time":0.6794002206,"remaining_time":0.02830834252},
{"learn":[3.097372213],"iteration":960,"passed_time":0.6799410533,"remaining_time":0.02759386168},
{"learn":[3.095981813],"iteration":961,"passed_time":0.6804640827,"remaining_time":0.02687903861},
{"learn":[3.095347452],"iteration":962,"passed_time":0.6810028416,"remaining_time":0.02616521821},
{"learn":[3.094728409],"iteration":963,"passed_time":0.6815353587,"remaining_time":0.02545152792},
{"learn":[3.094118537],"iteration":964,"passed_time":0.6820829541,"remaining_time":0.02473875999},
{"learn":[3.093793695],"iteration":965,"passed_time":0.6825778408,"remaining_time":0.02402447887},
{"learn":[3.092581602],"iteration":966,"passed_time":0.6830741703,"remaining_time":0.02331070074},
{"learn":[3.091694202],"iteration":967,"passed_time":0.6835922804,"remaining_time":0.02259809192},
{"learn":[3.090298312],"iteration":968,"passed_time":0.6841019548,"remaining_time":0.02188561465},
{"learn":[3.090020107],"iteration":969,"passed_time":0.6846134426,"remaining_time":0.02117361163},
{"learn":[3.088949869],"iteration":970,"passed_time":0.6851162642,"remaining_time":0.02046176278},
{"learn":[3.086700204],"iteration":971,"passed_time":0.6856179436,"remaining_time":0.01975031113},
{"learn":[3.086584317],"iteration":972,"passed_time":0.6861063482,"remaining_time":0.0190389223},
{"learn":[3.084850742],"iteration":973,"passed_time":0.6866226149,"remaining_time":0.0183287351},
{"learn":[3.084239948],"iteration":974,"passed_time":0.6871334114,"remaining_time":0.01761880542},
{"learn":[3.082561673],"iteration":975,"passed_time":0.6876600376,"remaining_time":0.01690967305},
{"learn":[3.07991814],"iteration":976,"passed_time":0.6881653037,"remaining_time":0.01620041145},
{"learn":[3.079350277],"iteration":977,"passed_time":0.6886707702,"remaining_time":0.01549157152},
{"learn":[3.077637462],"iteration":978,"passed_time":0.6891795129,"remaining_time":0.01478321733},
{"learn":[3.076733301],"iteration":979,"passed_time":0.6896823144,"remaining_time":0.01407514927},
{"learn":[3.07594065],"iteration":980,"passed_time":0.6901997734,"remaining_time":0.01336778358},
{"learn":[3.072594655],"iteration":981,"passed_time":0.6907092975,"remaining_time":0.01266065922},
{"learn":[3.071977674],"iteration":982,"passed_time":0.6912243319,"remaining_time":0.01195403219},
{"learn":[3.069532634],"iteration":983,"passed_time":0.6917340063,"remaining_time":0.01124770742},
{"learn":[3.068870784],"iteration":984,"passed_time":0.6922306062,"remaining_time":0.01054158284},
{"learn":[3.068801463],"iteration":985,"passed_time":0.6927196019,"remaining_time":0.009835775281},
{"learn":[3.067433249],"iteration":986,"passed_time":0.6933207175,"remaining_time":0.009131883818},
{"learn":[3.065611456],"iteration":987,"passed_time":0.6938730618,"remaining_time":0.008427608038},
{"learn":[3.063039162],"iteration":988,"passed_time":0.6944100374,"remaining_time":0.007723468565},
{"learn":[3.06177873],"iteration":989,"passed_time":0.6950635611,"remaining_time":0.007020844052},
{"learn":[3.061689148],"iteration":990,"passed_time":0.6955854784,"remaining_time":0.006317123417},
{"learn":[3.058984039],"iteration":991,"passed_time":0.6961561571,"remaining_time":0.005614162557},
{"learn":[3.057492984],"iteration":992,"passed_time":0.6967573929,"remaining_time":0.004911683535},
{"learn":[3.057290731],"iteration":993,"passed_time":0.6973526977,"remaining_time":0.00420937242},
{"learn":[3.056068348],"iteration":994,"passed_time":0.6978536157,"remaining_time":0.003506802089},
{"learn":[3.054987307],"iteration":995,"passed_time":0.698350426,"remaining_time":0.002804620185},
{"learn":[3.054200234],"iteration":996,"passed_time":0.6988649194,"remaining_time":0.002102903469},
{"learn":[3.052732869],"iteration":997,"passed_time":0.6993872375,"remaining_time":0.00140157763},
{"learn":[3.051787862],"iteration":998,"passed_time":0.6998901592,"remaining_time":0.00070059075},
{"learn":[3.051366222],"iteration":999,"passed_time":0.7003923797,"remaining_time":0}
]}